Workbook

Sheet NiveauMaturité
A2: Score | B2: Niveau | C2: Maturité | D2: Symbole
A3: 0 | B3: Inexistant | C3: L'entreprise n'a entrepris aucune démarche et n'a pas de projet à court terme. Elle n'a engagé aucune réflexion sur l'IA. Pas ou très peu d'usage professionnel, voire l'entreprise a bloqué l'accès aux solutions d'IA génératives.
A4: 1 | B4: En friche | C4: L'entreprise initie des expérimentations techniques et informelles autour de l'IA, portées par un leadership sensibilisé et des compétences externes ponctuelles. Cependant, la démarche manque encore de stratégie globale, de gouvernance des données et d'adhésion collective pour structurer ces opportunités.
A5: 2 | B5: En exploration | C5: L'entreprise a pris conscience du potentiel offert par les données. Commence à s'interroger, à tester, est à la recherche de solutions. Certains collaborateurs utilisent des outils individuellement (souvent sans supervision). La direction commence à s'interroger et à tester quelques outils sur étagère, sans stratégie définie.
A6: 3 | B6: En chantier | C6: L'entreprise a entrepris des actions ciblées mais la démarche n'est pas encore structurée (données non centralisées, commence à recruter, gouvernance peu travaillée). Elle commence à développer ou intégrer des solutions IA et à former ses collaborateurs. La démarche n'est pas encore structurée : la gouvernance (charte IA, rôles & responsabilité, sécurité des données) est encore inexistante ou faiblement travaillée.
A7: 4 | B7: En exploitation | C7: L'entreprise est engagée dans une approche structurée et a déployé des outils ou une infrastructure. Elle est engagée dans une approche structurée. A défini des règles d'usage claires et intégré l'IA dans le quotidiens des métiers.
A8: 5 | B8: En pilotage | C8: L'IA est un moteur de croissance piloté au niveau stratégique. L'usage est généralisé pour tous les collaborateurs. L'entreprise dispose de compétences internes et crée ses propres solutions. Le ROI est mesuré.

Sheet IndexQuestions
A1: MATURITE IA
A2: Modèle | B2: 5 dimensions × 3 étapes : Potentiel / Stratégie / Culture / Cpompétences / Gouvernance x Émergence / Structuration / Industrialisation. Chaque onglet transforme un score en diagnostic et actions de progression.
A3: Question | B3: Axe | C3: type | D3: Détail | E3: Thème | F3: Progression
A4: Q01 | B4: POTENTIEL | C4: Emergence | D4: Soutien à l'IA | E4: Quelles sont les infrastructures technologiques en place pour soutenir des projets d’IA ? | F4: Identifier → Explorer → Développer → Transformer
A5: Q02 | B5: POTENTIEL | C5: Structuration | D5: Data | E5: Dans quelle mesure l’entreprise dispose-t-elle de données accessibles, fiables et exploitables pour ses usages d’IA ?
A6: Q03 | B6: POTENTIEL | C6: Industrialisation | D6: Cas d'usage potentiels | E6: Dans quelle mesure les activités de l’entreprise présentent-elles un potentiel d’application de l’IA ?
A7: Q04 | B7: STRATÉGIE | C7: Emergence | D7: Ambition IA | E7: Quel est le niveau d’ambition de l’entreprise concernant l’IA ? | F7: Ambition → Roadmap → Portfolio
A8: Q05 | B8: STRATÉGIE | C8: Structuration | D8: Feuille de route | E8: Dans quelle mesure l’entreprise dispose-t-elle d’une feuille de route pour mettre en œuvre son ambition IA ?
A9: Q06 | B9: STRATÉGIE | C9: Industrialisation | D9: Portefeuille/priorisation | E9: Dans quelle mesure les initiatives et cas d’usage IA sont-ils priorisés en fonction des enjeux de l’entreprise ?
A10: Q07 | B10: CULTURE | C10: Emergence | D10: Leadership | E10: Dans quelle mesure les dirigeants et managers favorisent-ils l’adoption de l’IA dans l’entreprise ? | F10: Sensibilisation → Acceptation → Appropriation
A11: Q08 | B11: CULTURE | C11: Structuration | D11: Appropriation | E11: Dans quelle mesure les collaborateurs sont-ils prêts à adopter et utiliser l’IA dans leur activité ?
A12: Q09 | B12: CULTURE | C12: Industrialisation | D12: Apprentissage & collaboration | E12: Dans quelle mesure l’entreprise favorise-t-elle l’apprentissage, l’expérimentation et le partage autour de l’IA ?
A13: Q10 | B13: COMPÉTENCES | C13: Emergence | D13: Capacité interne | E13: Dans quelle mesure l’entreprise dispose-t-elle des compétences internes nécessaires pour concevoir, développer, déployer et exploiter des solutions d’IA ? | F13: Posséder → Développer → Adapter
A14: Q11 | B14: COMPÉTENCES | C14: Structuration | D14: Développement des compétences | E14: Dans quelle mesure l’entreprise développe-t-elle les compétences IA de ses collaborateurs ?
A15: Q12 | B15: COMPÉTENCES | C15: Industrialisation | D15: Adaptabilité / capacité à combler les lacunes | E15: Dans quelle mesure l’entreprise sait-elle identifier et combler ses lacunes en compétences IA ?
A16: Q13 | B16: GOUVERNANCE | C16: Emergence | D16: Cadre et responsabilités | E16: Dans quelle mesure l’entreprise dispose-t-elle d’un cadre de gouvernance pour encadrer l’utilisation de l’IA ? | F16: Cadrer → Évaluer → Surveiller
A17: Q14 | B17: GOUVERNANCE | C17: Structuration | D17: Évaluation & validation | E17: Dans quelle mesure les projets et usages d’IA font-ils l’objet d’une évaluation et d’une validation avant leur mise en production ?
A18: Q15 | B18: GOUVERNANCE | C18: Industrialisation | D18: Surveillance & cycle de vie | E18: Dans quelle mesure les solutions IA déployées sont-elles surveillées et réévaluées pendant leur cycle de vie ?

Sheet Questions
A1: N° | B1: Axe | C1: Type | D1: Question | E1: Réponses Potentielles
A2: =IndexQuestions!A4 -> Q01 | B2: =IndexQuestions!B4 -> POTENTIEL | C2: Emergence | D2: Quelles sont les infrastructures technologiques en place pour soutenir des projets d’IA ? | E2: 0- Absente : Aucune infrastructure ou capacité spécifique permettant de développer ou déployer des solutions IA. 1- Expérimentale : Des ressources IT/cloud existantes sont utilisées ponctuellement pour des expérimentations IA. 2- Disponible : Une infrastructure dédiée permettant de réaliser des projets IA existe, mais elle reste limitée, hétérogène ou peu standardisée. 3- Standardisée : Des environnements dédiés à l'IA sont standardisés, avec des capacités de calcul adaptées et des processus structurés de développement et de déploiement. 4- Optimisée : L'infrastructure est scalable, automatisée, sécurisée et optimisée pour les performances et les coûts des workloads IA. 5- À l'échelle de l'entreprise : Une plateforme IA gouvernée et industrialisée permet de supporter de nombreux cas d'usage, différents modèles et des déploiements à grande échelle, avec optimisation continue.
A3: Q02 | B3: Potentiel | C3: Structuration | D3: Dans quelle mesure l’entreprise dispose-t-elle de données accessibles, fiables et exploitables pour ses usages d’IA ? | E3: 0- Absente : Aucune donnée pertinente identifiée. 1- Fragmentée : Données dispersées, difficilement accessibles et de qualité incertaine. 2- Disponible : Données pertinentes disponibles pour certains usages, mais encore hétérogènes ou difficiles à exploiter. 3- Exploitable : Données accessibles, structurées ou préparées et suffisamment fiables pour développer des solutions IA. 4- Industrialisée : Données gouvernées, cataloguées, contrôlées et alimentées par des pipelines permettant des usages IA reproductibles. 5- Data-ready : Environnement data industrialisé permettant d'alimenter, à grande échelle, différents usages IA avec qualité, traçabilité, automatisation et réutilisabilité.
A4: Q03 | B4: Potentiel | C4: Industrialisation | D4: Dans quelle mesure les activités de l’entreprise présentent-elles un potentiel d’application de l’IA ? | E4: 0- Aucun potentiel identifié : Aucun cas d'usage IA pertinent identifié. 1- Potentiel limité : Quelques opportunités ponctuelles, avec un impact potentiel limité. 2- Potentiel identifié : Plusieurs cas d'usage pertinents ont été identifiés dans certaines activités. 3- Potentiel significatif : L'IA peut améliorer significativement plusieurs processus, produits ou services. 4- Potentiel élevé : L'IA peut transformer plusieurs activités clés ou générer de nouvelles sources importantes de valeur. 5- Potentiel stratégique : L'IA est susceptible de transformer en profondeur le modèle opérationnel, les produits/services ou les sources de valeur de l'entreprise.
A5: Q04 | B5: Stratégie | C5: Emergence | D5: Quel est le niveau d’ambition de l’entreprise concernant l’IA ? | E5: 0- Absente : L’IA ne fait pas partie des réflexions ou ambitions de l’entreprise. 1- Exploratoire : L’entreprise commence à explorer les possibilités offertes par l’IA. 2- Expérimentation : L’entreprise affiche une volonté de développer l’IA à travers quelques initiatives ciblées. 3- Ambition définie : Des objectifs explicites concernant l’IA sont définis au niveau de l’entreprise ou de plusieurs activités. 4- Transformation : L’IA constitue un levier identifié de transformation des activités, produits, services ou opérations. 5- Ambition stratégique : L’IA est considérée comme un levier majeur d’évolution du positionnement et/ou du modèle économique de l’entreprise.
A6: Q05 | B6: Stratégie | C6: Structuration | D6: Dans quelle mesure l’entreprise dispose-t-elle d’une feuille de route pour mettre en œuvre son ambition IA ? | E6: 0- Aucune feuille de route : Aucune action ou trajectoire IA définie. 1- Initiatives ponctuelles : Quelques initiatives existent sans trajectoire commune. 2- Roadmap émergente : Des initiatives sont regroupées et une première trajectoire est en cours de définition. 3- Roadmap structurée : Une feuille de route IA définit des initiatives, des échéances et des objectifs. 4- Roadmap pilotée : La feuille de route est intégrée aux plans de l’entreprise et régulièrement pilotée avec des indicateurs. 5- Transformation orchestrée : Une trajectoire pluriannuelle coordonne les initiatives IA, leur passage à l’échelle et leur évolution en fonction des résultats et des priorités de l’entreprise.
A7: Q06 | B7: Stratégie | C7: Industrialisation | D7: Dans quelle mesure les initiatives et cas d’usage IA sont-ils priorisés en fonction des enjeux de l’entreprise ? | E7: 0- Aucun cas d’usage : Aucun cas d’usage IA identifié. 1- Exploration : Quelques cas d’usage sont identifiés sans véritable priorisation. 2- Identification : Plusieurs cas d’usage sont recensés et font l’objet d’une première analyse. 3- Priorisation : Les cas d’usage sont priorisés selon des critères explicites tels que valeur, faisabilité, risques ou effort. 4- Portefeuille piloté : Les initiatives sont gérées comme un portefeuille, avec arbitrage des investissements et suivi de leur progression. 5- Optimisation continue : Le portefeuille est régulièrement réévalué en fonction de la valeur créée, des résultats obtenus, des nouvelles opportunités et de l’évolution des priorités de l’entreprise.
A8: Q07 | B8: Culture | C8: Emergence | D8: Dans quelle mesure les dirigeants et managers favorisent-ils l’adoption de l’IA dans l’entreprise ? | E8: 0- Absence d'implication : Les dirigeants et managers ne manifestent pas d'intérêt ou d'implication vis-à-vis de l'IA. 1- Sensibilisation : Le sujet est connu des dirigeants et managers, mais sans implication concrète. 2- Soutien ponctuel : Certains dirigeants ou managers soutiennent des initiatives IA, principalement au niveau de projets individuels. 3- Soutien managérial : Les managers encouragent l'expérimentation et l'utilisation de l'IA dans leurs équipes. 4- Leadership actif : Les dirigeants et managers portent activement l'adoption de l'IA et accompagnent sa diffusion dans l'entreprise. 5- Leadership exemplaire : Le leadership IA est visible dans les pratiques managériales et les dirigeants incarnent eux-mêmes l'utilisation et l'adoption de l'IA.
A9: Q08 | B9: Culture | C9: Structuration | D9: Dans quelle mesure les collaborateurs sont-ils prêts à adopter et utiliser l’IA dans leur activité ? | E9: 0- Résistance : L'IA suscite principalement de la crainte, de la méfiance ou une résistance à son utilisation. 1- Distance : Les collaborateurs connaissent le sujet mais restent largement indifférents ou peu concernés. 2- Curiosité : Une partie des collaborateurs manifeste de l'intérêt et commence à expérimenter l'IA. 3- Acceptation : L'utilisation de l'IA est globalement acceptée et commence à entrer dans les pratiques de travail. 4- Appropriation : Les collaborateurs utilisent spontanément l'IA pour améliorer leurs activités et partagent leurs expériences. 5- Transformation des pratiques : Les collaborateurs contribuent activement à faire évoluer les usages de l'IA et intègrent celle-ci dans leurs pratiques professionnelles.
A10: Q09 | B10: Culture | C10: Industrialisation | D10: Dans quelle mesure l’entreprise favorise-t-elle l’apprentissage, l’expérimentation et le partage autour de l’IA ? | E10: 0- Aucun dispositif : Aucun dispositif d'apprentissage, d'expérimentation ou de partage autour de l'IA. 1- Initiatives informelles : Des échanges ou expérimentations existent de manière informelle entre quelques collaborateurs. 2- Initiatives ponctuelles : Des ateliers, formations, communautés ou expérimentations sont organisés ponctuellement. 3- Dispositifs réguliers : Des dispositifs réguliers permettent aux collaborateurs d'apprendre, expérimenter et partager autour de l'IA. 4- Communautés actives : Des communautés, réseaux ou espaces de collaboration structurés favorisent la diffusion des pratiques et des retours d'expérience. 5- Apprentissage continu : L'expérimentation, le partage et l'apprentissage autour de l'IA sont intégrés durablement dans les modes de fonctionnement de l'entreprise.
A11: Q10 | B11: Compétences | C11: Emergence | D11: Dans quelle mesure l’entreprise dispose-t-elle des compétences internes nécessaires pour concevoir, développer, déployer et exploiter des solutions d’IA ? | E11: 0- Absentes : L'entreprise ne dispose pas de compétences internes identifiées en IA. 1- Très limitées : Quelques personnes possèdent des connaissances ou compétences IA, sans capacité collective structurée. 2- Partielles : Une équipe ou plusieurs personnes disposent de compétences permettant de réaliser certains projets IA, mais des compétences importantes manquent. 3- Opérationnelles : L'entreprise dispose des principales compétences nécessaires pour développer et mettre en œuvre des projets IA. 4- Complètes : Les compétences couvrent les différentes dimensions nécessaires : data, IA/ML, ingénierie, intégration, déploiement et usages métiers. 5- Multidisciplinaires : L'entreprise dispose d'une capacité interne multidisciplinaire permettant de concevoir, industrialiser et faire évoluer des solutions IA de manière autonome.
A12: Q11 | B12: Compétences | C12: Structuration | D12: Dans quelle mesure l’entreprise développe-t-elle les compétences IA de ses collaborateurs ? | E12: 0- Aucun développement : Aucun dispositif de développement des compétences IA. 1- Sensibilisation : Des actions ponctuelles de sensibilisation ou d'initiation sont proposées. 2- Formation ciblée : Des formations sont proposées à certaines populations ou pour certains besoins. 3- Parcours structurés : Des parcours de développement des compétences sont définis pour différentes catégories de collaborateurs. 4- Gestion des compétences : Les compétences IA sont identifiées, évaluées et développées en fonction des rôles et des besoins de l'entreprise. 5- Développement continu : L'entreprise dispose d'un dispositif continu permettant d'anticiper les évolutions des compétences IA, d'évaluer les acquis et d'adapter régulièrement les parcours.
A13: Q12 | B13: Compétences | C13: Industrialisation | D13: Dans quelle mesure l’entreprise sait-elle identifier et combler ses lacunes en compétences IA ? | E13: 0- Aucune capacité : Les besoins et lacunes en compétences IA ne sont pas identifiés et aucun recours externe n'est organisé. 1- Réponse ponctuelle : Les compétences manquantes sont traitées au cas par cas, principalement par recours à des prestataires ou experts externes. 2- Recours régulier : L'entreprise fait régulièrement appel à des compétences externes pour compléter ses capacités internes. 3- Approche structurée : Les lacunes sont identifiées et font l'objet d'une stratégie combinant recrutement, formation et recours à des partenaires externes. 4- Écosystème de compétences : L'entreprise dispose d'un réseau structuré de partenaires, experts, fournisseurs ou institutions permettant de compléter rapidement ses compétences internes. 5- Gestion dynamique des capacités : L'entreprise anticipe ses besoins en compétences et ajuste continuellement le mix entre développement interne, recrutement, mobilité et recours à l'écosystème externe.
A14: Q13 | B14: Gouvernance | C14: Emergence | D14: Dans quelle mesure l’entreprise dispose-t-elle d’un cadre de gouvernance pour encadrer l’utilisation de l’IA ? | E14: 0- Aucun cadre : Aucun principe, règle ou responsabilité n'est défini pour l'utilisation de l'IA. 1- Principes informels : Des principes ou consignes existent, mais ils restent informels et peu diffusés. 2- Règles partielles : Des règles existent pour certains usages ou risques, mais leur couverture reste limitée. 3- Cadre formalisé : Un cadre formalisé définit les principales règles, responsabilités et conditions d'utilisation de l'IA. 4- Gouvernance structurée : Le cadre couvre notamment les risques, la sécurité, les données, la conformité, l'éthique et les responsabilités, avec des rôles clairement définis. 5- Gouvernance intégrée : La gouvernance IA est intégrée aux processus de l'entreprise et évolue régulièrement en fonction des risques, des usages, des réglementations et des pratiques de référence.
... A16: Q15 | B16: Gouvernance | C16: Industrialisation | D16: Dans quelle mesure les solutions IA déployées sont-elles surveillées et réévaluées pendant leur cycle de vie ? | E16: 0- Aucun suivi : Les solutions IA ne font pas l'objet d'un suivi après leur déploiement. 1- Suivi ponctuel : Le fonctionnement des solutions est vérifié ponctuellement, généralement en cas de problème. 2- Suivi partiel : Certaines métriques ou retours utilisateurs sont suivis, mais de manière inégale. 3- Suivi structuré : Des indicateurs sont définis et suivis régulièrement pour les solutions IA en production. 4- Suivi continu : Le suivi couvre notamment performance, qualité, sécurité, coûts, dérive des modèles et retours utilisateurs, avec des mécanismes d'alerte et d'action. 5- Gouvernance du cycle de vie : Les solutions IA sont surveillées et réévaluées sur l'ensemble de leur cycle de vie, avec des mécanismes permettant d'adapter, suspendre ou retirer une solution lorsque les conditions ou les risques évoluent.

Sheet Réponses
A1: Id | B1: Entreprise | C1: 1. Opportunités de valeur | D1: 2. Cas d'usage potentiels | E1: 3. Capacité à identifier les opportunités | F1: 4. Ambition IA | G1: 5. Feuille de route | H1: 6. Portefeuille/priorisation | I1: 7. Leadership | J1: 8. Appropriation | K1: 9. Apprentissage & collaboration | L1: 10. Capacité interne | M1: 11. Développement des compétences | N1: 12. Adaptabilité / capacité à combler les lacunes | O1: 13. Cadre et responsabilités | P1: 14. Évaluation & validation | Q1: 15. Surveillance & cycle de vie
A2: 1 | B2: EntrepriseA | C2: 1 | D2: 1 | E2: 1 | F2: 1 | G2: 1 | H2: 1 | I2: 1 | J2: 1 | K2: 1 | L2: 1 | M2: 1 | N2: 1 | O2: 1 | P2: 1 | Q2: 1
A3: 2 | B3: EntrepriseB | C3: 3 | D3: 3 | E3: 4 | F3: 5 | G3: 3 | H3: 2 | I3: 3 | J3: 3 | K3: 2 | L3: 3 | M3: 2 | N3: 1 | O3: 1 | P3: 1 | Q3: 1
A4: 3 | B4: EntrepriseC | C4: 5 | D4: 5 | E4: 5 | F4: 5 | G4: 5 | H4: 3 | I4: 2 | J4: 2 | K4: 2 | L4: 3 | M4: 2 | N4: 1 | O4: 1 | P4: 1 | Q4: 1
A5: 4 | B5: EntrepriseD | C5: 1 | D5: 1 | E5: 1 | F5: 2 | G5: 2 | H5: 3 | I5: 0 | J5: 0 | K5: 1 | L5: 5 | M5: 5 | N5: 3 | O5: 1 | P5: 2 | Q5: 3
A6: 5 | B6: EntrepriseE | C6: 0 | D6: 0 | E6: 0 | F6: 0 | G6: 0 | H6: 0 | I6: 0 | J6: 0 | K6: 0 | L6: 0 | M6: 0 | N6: 0 | O6: 0 | P6: 0 | Q6: 0

Sheet CalculAxes
A1: ID | B1: Répondant | C1: Potentiel | D1: Stratégie | E1: Culture | F1: Compétences | G1: Gouvernance | H1: Moyenne | I1: Indice d'Équilibre | J1: Niveau de Maturité
A2: =Réponses!A2 -> 1 | B2: =Réponses!B2 -> EntrepriseA | C2: =AVERAGE(Réponses!C2:E2) -> 1 | D2: =AVERAGE(Réponses!F2:H2) -> 1 | E2: =AVERAGE(Réponses!I2:K2) -> 1 | F2: =AVERAGE(Réponses!L2:N2) -> 1 | G2: =AVERAGE(Réponses!O2:Q2) -> 1 | H2: =AVERAGE(C2:G2) -> 1 | I2: =AVEDEV(C2:G2) -> 0 | J2: =_xlfn.XLOOKUP(MATCH(ROUNDUP(H2,0),Tableau1618[Score],)-1,NiveauMaturité!$A$3:$A$8,NiveauMaturité!$B$3:$B$8) -> En friche
A3: =Réponses!A3 -> 2 | B3: =Réponses!B3 -> EntrepriseB | C3: =AVERAGE(Réponses!C3:E3) -> 3.3333333 | D3: =AVERAGE(Réponses!F3:H3) -> 3.3333333 | E3: =AVERAGE(Réponses!I3:K3) -> 2.6666667 | F3: =AVERAGE(Réponses!L3:N3) -> 2 | G3: =AVERAGE(Réponses!O3:Q3) -> 1 | H3: =AVERAGE(C3:G3) -> 2.4666667 | I3: =AVEDEV(C3:G3) -> 0.77333333 | J3: =_xlfn.XLOOKUP(MATCH(ROUNDUP(H3,0),Tableau1618[Score],)-1,NiveauMaturité!$A$3:$A$8,NiveauMaturité!$B$3:$B$8) -> En chantier
A4: =Réponses!A4 -> 3 | B4: =Réponses!B4 -> EntrepriseC | C4: =AVERAGE(Réponses!C4:E4) -> 5 | D4: =AVERAGE(Réponses!F4:H4) -> 4.3333333 | E4: =AVERAGE(Réponses!I4:K4) -> 2 | F4: =AVERAGE(Réponses!L4:N4) -> 2 | G4: =AVERAGE(Réponses!O4:Q4) -> 1 | H4: =AVERAGE(C4:G4) -> 2.8666667 | I4: =AVEDEV(C4:G4) -> 1.44 | J4: =_xlfn.XLOOKUP(MATCH(ROUNDUP(H4,0),Tableau1618[Score],)-1,NiveauMaturité!$A$3:$A$8,NiveauMaturité!$B$3:$B$8) -> En chantier
A5: =Réponses!A5 -> 4 | B5: =Réponses!B5 -> EntrepriseD | C5: =AVERAGE(Réponses!C5:E5) -> 1 | D5: =AVERAGE(Réponses!F5:H5) -> 2.3333333 | E5: =AVERAGE(Réponses!I5:K5) -> 0.33333333 | F5: =AVERAGE(Réponses!L5:N5) -> 4.3333333 | G5: =AVERAGE(Réponses!O5:Q5) -> 2 | H5: =AVERAGE(C5:G5) -> 2 | I5: =AVEDEV(C5:G5) -> 1.0666667 | J5: =_xlfn.XLOOKUP(MATCH(ROUNDUP(H5,0),Tableau1618[Score],)-1,NiveauMaturité!$A$3:$A$8,NiveauMaturité!$B$3:$B$8) -> En exploration
A6: =Réponses!A6 -> 5 | B6: =Réponses!B6 -> EntrepriseE | C6: =AVERAGE(Réponses!C6:E6) -> 0 | D6: =AVERAGE(Réponses!F6:H6) -> 0 | E6: =AVERAGE(Réponses!I6:K6) -> 0 | F6: =AVERAGE(Réponses!L6:N6) -> 0 | G6: =AVERAGE(Réponses!O6:Q6) -> 0 | H6: =AVERAGE(C6:G6) -> 0 | I6: =AVEDEV(C6:G6) -> 0 | J6: =_xlfn.XLOOKUP(MATCH(ROUNDUP(H6,0),Tableau1618[Score],)-1,NiveauMaturité!$A$3:$A$8,NiveauMaturité!$B$3:$B$8) -> Inexistant
A24: ID | B24: Répondant | C24: Emergence | D24: Structuration | E24: Industrialisation | F24: Indice d'Équilibre
A25: =Réponses!A2 -> 1 | B25: =Réponses!B2 -> EntrepriseA | C25: =AVERAGE(Réponses!C2,Réponses!F2,Réponses!I2,Réponses!L2,Réponses!O2) -> 1 | D25: =AVERAGE(Réponses!D2,Réponses!G2,Réponses!J2,Réponses!M2,Réponses!P2) -> 1 | E25: =AVERAGE(Réponses!E2,Réponses!H2,Réponses!K2,Réponses!N2,Réponses!Q2) -> 1 | F25: =AVEDEV(C25:E25) -> 0
A26: =Réponses!A3 -> 2 | B26: =Réponses!B3 -> EntrepriseB | C26: =AVERAGE(Réponses!C3,Réponses!F3,Réponses!I3,Réponses!L3,Réponses!O3) -> 3 | D26: =AVERAGE(Réponses!D3,Réponses!G3,Réponses!J3,Réponses!M3,Réponses!P3) -> 2.4 | E26: =AVERAGE(Réponses!E3,Réponses!H3,Réponses!K3,Réponses!N3,Réponses!Q3) -> 2 | F26: =AVEDEV(C26:E26) -> 0.35555556
A27: =Réponses!A4 -> 3 | B27: =Réponses!B4 -> EntrepriseC | C27: =AVERAGE(Réponses!C4,Réponses!F4,Réponses!I4,Réponses!L4,Réponses!O4) -> 3.2 | D27: =AVERAGE(Réponses!D4,Réponses!G4,Réponses!J4,Réponses!M4,Réponses!P4) -> 3 | E27: =AVERAGE(Réponses!E4,Réponses!H4,Réponses!K4,Réponses!N4,Réponses!Q4) -> 2.4 | F27: =AVEDEV(C27:E27) -> 0.31111111
A28: =Réponses!A5 -> 4 | B28: =Réponses!B5 -> EntrepriseD | C28: =AVERAGE(Réponses!C5,Réponses!F5,Réponses!I5,Réponses!L5,Réponses!O5) -> 1.8 | D28: =AVERAGE(Réponses!D5,Réponses!G5,Réponses!J5,Réponses!M5,Réponses!P5) -> 2 | E28: =AVERAGE(Réponses!E5,Réponses!H5,Réponses!K5,Réponses!N5,Réponses!Q5) -> 2.2 | F28: =AVEDEV(C28:E28) -> 0.13333333
A29: =Réponses!A6 -> 5 | B29: =Réponses!B6 -> EntrepriseE | C29: =AVERAGE(Réponses!C6,Réponses!F6,Réponses!I6,Réponses!L6,Réponses!O6) -> 0 | D29: =AVERAGE(Réponses!D6,Réponses!G6,Réponses!J6,Réponses!M6,Réponses!P6) -> 0 | E29: =AVERAGE(Réponses!E6,Réponses!H6,Réponses!K6,Réponses!N6,Réponses!Q6) -> 0 | F29: =AVEDEV(C29:E29) -> 0

Sheet TMatrice
B1: 1 — Émergence | C1: 2 — Structuration | D1: 3 — Industrialisation | R1: ce qui est déjà acquis ; | AC1: ce qui bloque l'étape suivante ; | AN1: les capacités à acquérir ; | AY1: les actions prioritaires ; | BJ1: les résultats attendus.
A2: ce qui est déjà acquis ; | B2: ="Q" & J2 & "!" & M2 -> Q01!D | C2: ="Q" & K2 & "!" & N2 -> Q02!D | D2: ="Q" & L2 & "!" & O2 -> Q03!D | E2: Potentiel | J2: 01 | K2: 02 | L2: 03 | M2: D | N2: D | O2: D | R2: 01 | S2: 02 | T2: 03 | U2: D | V2: D | W2: D | Y2: ="Q" & R2 & "!" & U2 -> Q01!D | Z2: ="Q" & S2 & "!" & V2 -> Q02!D | AA2: ="Q" & T2 & "!" & W2 -> Q03!D | AC2: 01 | AD2: 02 | AE2: 03 | AF2: E | AG2: E | AH2: E | AJ2: ="Q" & AC2 & "!" & AF2 -> Q01!E | AK2: ="Q" & AD2 & "!" & AG2 -> Q02!E | AL2: ="Q" & AE2 & "!" & AH2 -> Q03!E | AN2: 01 | AO2: 02 | AP2: 03 | AQ2: F | AR2: F | AS2: F | AU2: ="Q" & AN2 & "!" & AQ2 -> Q01!F | AV2: ="Q" & AO2 & "!" & AR2 -> Q02!F | AW2: ="Q" & AP2 & "!" & AS2 -> Q03!F | AY2: 01 | AZ2: 02 | BA2: 03 | BB2: G | BC2: G | BD2: G | BF2: ="Q" & AY2 & "!" & BB2 -> Q01!G | BG2: ="Q" & AZ2 & "!" & BC2 -> Q02!G | BH2: ="Q" & BA2 & "!" & BD2 -> Q03!G | BJ2: 01 | BK2: 02 | BL2: 03 | BM2: H | BN2: H | BO2: H | BQ2: ="Q" & BJ2 & "!" & BM2 -> Q01!H | BR2: ="Q" & BK2 & "!" & BN2 -> Q02!H | BS2: ="Q" & BL2 & "!" & BO2 -> Q03!H
A3: ce qui bloque l'étape suivante ; | B3: ="Q" & J3 & "!" & M3 -> Q01!E | C3: ="Q" & K3 & "!" & N3 -> Q02!E | D3: ="Q" & L3 & "!" & O3 -> Q03!E | J3: 01 | K3: 02 | L3: 03 | M3: E | N3: E | O3: E | R3: 04 | S3: 05 | T3: 06 | U3: D | V3: D | W3: D | Y3: ="Q" & R3 & "!" & U3 -> Q04!D | Z3: ="Q" & S3 & "!" & V3 -> Q05!D | AA3: ="Q" & T3 & "!" & W3 -> Q06!D | AC3: 04 | AD3: 05 | AE3: 06 | AF3: E | AG3: E | AH3: E | AJ3: ="Q" & AC3 & "!" & AF3 -> Q04!E | AK3: ="Q" & AD3 & "!" & AG3 -> Q05!E | AL3: ="Q" & AE3 & "!" & AH3 -> Q06!E | AN3: 04 | AO3: 05 | AP3: 06 | AQ3: F | AR3: F | AS3: F | AU3: ="Q" & AN3 & "!" & AQ3 -> Q04!F | AV3: ="Q" & AO3 & "!" & AR3 -> Q05!F | AW3: ="Q" & AP3 & "!" & AS3 -> Q06!F | AY3: 04 | AZ3: 05 | BA3: 06 | BB3: G | BC3: G | BD3: G | BF3: ="Q" & AY3 & "!" & BB3 -> Q04!G | BG3: ="Q" & AZ3 & "!" & BC3 -> Q05!G | BH3: ="Q" & BA3 & "!" & BD3 -> Q06!G | BJ3: 04 | BK3: 05 | BL3: 06 | BM3: H | BN3: H | BO3: H | BQ3: ="Q" & BJ3 & "!" & BM3 -> Q04!H | BR3: ="Q" & BK3 & "!" & BN3 -> Q05!H | BS3: ="Q" & BL3 & "!" & BO3 -> Q06!H
A4: les capacités à construire ; | B4: ="Q" & J4 & "!" & M4 -> Q01!F | C4: ="Q" & K4 & "!" & N4 -> Q02!F | D4: ="Q" & L4 & "!" & O4 -> Q03!F | J4: 01 | K4: 02 | L4: 03 | M4: F | N4: F | O4: F | R4: 07 | S4: 08 | T4: 09 | U4: D | V4: D | W4: D | Y4: ="Q" & R4 & "!" & U4 -> Q07!D | Z4: ="Q" & S4 & "!" & V4 -> Q08!D | AA4: ="Q" & T4 & "!" & W4 -> Q09!D | AC4: 07 | AD4: 08 | AE4: 09 | AF4: E | AG4: E | AH4: E | AJ4: ="Q" & AC4 & "!" & AF4 -> Q07!E | AK4: ="Q" & AD4 & "!" & AG4 -> Q08!E | AL4: ="Q" & AE4 & "!" & AH4 -> Q09!E | AN4: 07 | AO4: 08 | AP4: 09 | AQ4: F | AR4: F | AS4: F | AU4: ="Q" & AN4 & "!" & AQ4 -> Q07!F | AV4: ="Q" & AO4 & "!" & AR4 -> Q08!F | AW4: ="Q" & AP4 & "!" & AS4 -> Q09!F | AY4: 07 | AZ4: 08 | BA4: 09 | BB4: G | BC4: G | BD4: G | BF4: ="Q" & AY4 & "!" & BB4 -> Q07!G | BG4: ="Q" & AZ4 & "!" & BC4 -> Q08!G | BH4: ="Q" & BA4 & "!" & BD4 -> Q09!G | BJ4: 07 | BK4: 08 | BL4: 09 | BM4: H | BN4: H | BO4: H | BQ4: ="Q" & BJ4 & "!" & BM4 -> Q07!H | BR4: ="Q" & BK4 & "!" & BN4 -> Q08!H | BS4: ="Q" & BL4 & "!" & BO4 -> Q09!H
A5: les actions prioritaires ; | B5: ="Q" & J5 & "!" & M5 -> Q01!G | C5: ="Q" & K5 & "!" & N5 -> Q02!G | D5: ="Q" & L5 & "!" & O5 -> Q03!G | J5: 01 | K5: 02 | L5: 03 | M5: G | N5: G | O5: G | R5: 10 | S5: 11 | T5: 12 | U5: D | V5: D | W5: D | Y5: ="Q" & R5 & "!" & U5 -> Q10!D | Z5: ="Q" & S5 & "!" & V5 -> Q11!D | AA5: ="Q" & T5 & "!" & W5 -> Q12!D | AC5: 10 | AD5: 11 | AE5: 12 | AF5: E | AG5: E | AH5: E | AJ5: ="Q" & AC5 & "!" & AF5 -> Q10!E | AK5: ="Q" & AD5 & "!" & AG5 -> Q11!E | AL5: ="Q" & AE5 & "!" & AH5 -> Q12!E | AN5: 10 | AO5: 11 | AP5: 12 | AQ5: F | AR5: F | AS5: F | AU5: ="Q" & AN5 & "!" & AQ5 -> Q10!F | AV5: ="Q" & AO5 & "!" & AR5 -> Q11!F | AW5: ="Q" & AP5 & "!" & AS5 -> Q12!F | AY5: 10 | AZ5: 11 | BA5: 12 | BB5: G | BC5: G | BD5: G | BF5: ="Q" & AY5 & "!" & BB5 -> Q10!G | BG5: ="Q" & AZ5 & "!" & BC5 -> Q11!G | BH5: ="Q" & BA5 & "!" & BD5 -> Q12!G | BJ5: 10 | BK5: 11 | BL5: 12 | BM5: H | BN5: H | BO5: H | BQ5: ="Q" & BJ5 & "!" & BM5 -> Q10!H | BR5: ="Q" & BK5 & "!" & BN5 -> Q11!H | BS5: ="Q" & BL5 & "!" & BO5 -> Q12!H
A6: les résultats attendus. | B6: ="Q" & J6 & "!" & M6 -> Q01!H | C6: ="Q" & K6 & "!" & N6 -> Q02!H | D6: ="Q" & L6 & "!" & O6 -> Q03!H | J6: 01 | K6: 02 | L6: 03 | M6: H | N6: H | O6: H | R6: 13 | S6: 14 | T6: 15 | U6: D | V6: D | W6: D | Y6: ="Q" & R6 & "!" & U6 -> Q13!D | Z6: ="Q" & S6 & "!" & V6 -> Q14!D | AA6: ="Q" & T6 & "!" & W6 -> Q15!D | AC6: 13 | AD6: 14 | AE6: 15 | AF6: E | AG6: E | AH6: E | AJ6: ="Q" & AC6 & "!" & AF6 -> Q13!E | AK6: ="Q" & AD6 & "!" & AG6 -> Q14!E | AL6: ="Q" & AE6 & "!" & AH6 -> Q15!E | AN6: 13 | AO6: 14 | AP6: 15 | AQ6: F | AR6: F | AS6: F | AU6: ="Q" & AN6 & "!" & AQ6 -> Q13!F | AV6: ="Q" & AO6 & "!" & AR6 -> Q14!F | AW6: ="Q" & AP6 & "!" & AS6 -> Q15!F | AY6: 13 | AZ6: 14 | BA6: 15 | BB6: G | BC6: G | BD6: G | BF6: ="Q" & AY6 & "!" & BB6 -> Q13!G | BG6: ="Q" & AZ6 & "!" & BC6 -> Q14!G | BH6: ="Q" & BA6 & "!" & BD6 -> Q15!G | BJ6: 13 | BK6: 14 | BL6: 15 | BM6: H | BN6: H | BO6: H | BQ6: ="Q" & BJ6 & "!" & BM6 -> Q13!H | BR6: ="Q" & BK6 & "!" & BN6 -> Q14!H | BS6: ="Q" & BL6 & "!" & BO6 -> Q15!H
A8: ce qui est déjà acquis ; | B8: ="Q" & J8 & "!" & M8 -> Q04!D | C8: ="Q" & K8 & "!" & N8 -> Q05!D | D8: ="Q" & L8 & "!" & O8 -> Q06!D | E8: Stratégie | J8: 04 | K8: 05 | L8: 06 | M8: D | N8: D | O8: D
A9: ce qui bloque l'étape suivante ; | B9: ="Q" & J9 & "!" & M9 -> Q04!E | C9: ="Q" & K9 & "!" & N9 -> Q05!E | D9: ="Q" & L9 & "!" & O9 -> Q06!E | J9: 04 | K9: 05 | L9: 06 | M9: E | N9: E | O9: E
A10: les capacités à construire ; | B10: ="Q" & J10 & "!" & M10 -> Q04!F | C10: ="Q" & K10 & "!" & N10 -> Q05!F | D10: ="Q" & L10 & "!" & O10 -> Q06!F | J10: 04 | K10: 05 | L10: 06 | M10: F | N10: F | O10: F
A11: les actions prioritaires ; | B11: ="Q" & J11 & "!" & M11 -> Q04!G | C11: ="Q" & K11 & "!" & N11 -> Q05!G | D11: ="Q" & L11 & "!" & O11 -> Q06!G | J11: 04 | K11: 05 | L11: 06 | M11: G | N11: G | O11: G
A12: les résultats attendus. | B12: ="Q" & J12 & "!" & M12 -> Q04!H | C12: ="Q" & K12 & "!" & N12 -> Q05!H | D12: ="Q" & L12 & "!" & O12 -> Q06!H | J12: 04 | K12: 05 | L12: 06 | M12: H | N12: H | O12: H | R12: Potentiel
R13: Stratégie
A14: ce qui est déjà acquis ; | B14: ="Q" & J14 & "!" & M14 -> Q07!D | C14: ="Q" & K14 & "!" & N14 -> Q08!D | D14: ="Q" & L14 & "!" & O14 -> Q09!D | E14: Culture | J14: 07 | K14: 08 | L14: 09 | M14: D | N14: D | O14: D | R14: Culture
A15: ce qui bloque l'étape suivante ; | B15: ="Q" & J15 & "!" & M15 -> Q07!E | C15: ="Q" & K15 & "!" & N15 -> Q08!E | D15: ="Q" & L15 & "!" & O15 -> Q09!E | J15: 07 | K15: 08 | L15: 09 | M15: E | N15: E | O15: E | R15: Compétences
A16: les capacités à construire ; | B16: ="Q" & J16 & "!" & M16 -> Q07!F | C16: ="Q" & K16 & "!" & N16 -> Q08!F | D16: ="Q" & L16 & "!" & O16 -> Q09!F | J16: 07 | K16: 08 | L16: 09 | M16: F | N16: F | O16: F | R16: Gouvernance
A17: les actions prioritaires ; | B17: ="Q" & J17 & "!" & M17 -> Q07!G | C17: ="Q" & K17 & "!" & N17 -> Q08!G | D17: ="Q" & L17 & "!" & O17 -> Q09!G | J17: 07 | K17: 08 | L17: 09 | M17: G | N17: G | O17: G
A18: les résultats attendus. | B18: ="Q" & J18 & "!" & M18 -> Q07!H | C18: ="Q" & K18 & "!" & N18 -> Q08!H | D18: ="Q" & L18 & "!" & O18 -> Q09!H | J18: 07 | K18: 08 | L18: 09 | M18: H | N18: H | O18: H | Q18: La roadmap est ensuite construite en identifiant :
R19: ce qui est déjà acquis ;
A20: ce qui est déjà acquis ; | B20: ="Q" & J20 & "!" & M20 -> Q10!D | C20: ="Q" & K20 & "!" & N20 -> Q11!D | D20: ="Q" & L20 & "!" & O20 -> Q12!D | E20: Compétences | J20: 10 | K20: 11 | L20: 12 | M20: D | N20: D | O20: D | R20: ce qui bloque l'étape suivante ;
A21: ce qui bloque l'étape suivante ; | B21: ="Q" & J21 & "!" & M21 -> Q10!E | C21: ="Q" & K21 & "!" & N21 -> Q11!E | D21: ="Q" & L21 & "!" & O21 -> Q12!E | J21: 10 | K21: 11 | L21: 12 | M21: E | N21: E | O21: E | R21: les capacités à acquérir ;
A22: les capacités à construire ; | B22: ="Q" & J22 & "!" & M22 -> Q10!F | C22: ="Q" & K22 & "!" & N22 -> Q11!F | D22: ="Q" & L22 & "!" & O22 -> Q12!F | J22: 10 | K22: 11 | L22: 12 | M22: F | N22: F | O22: F | R22: les actions prioritaires ;
A23: les actions prioritaires ; | B23: ="Q" & J23 & "!" & M23 -> Q10!G | C23: ="Q" & K23 & "!" & N23 -> Q11!G | D23: ="Q" & L23 & "!" & O23 -> Q12!G | J23: 10 | K23: 11 | L23: 12 | M23: G | N23: G | O23: G | R23: les résultats attendus.
A24: les résultats attendus. | B24: ="Q" & J24 & "!" & M24 -> Q10!H | C24: ="Q" & K24 & "!" & N24 -> Q11!H | D24: ="Q" & L24 & "!" & O24 -> Q12!H | J24: 10 | K24: 11 | L24: 12 | M24: H | N24: H | O24: H
A26: ce qui est déjà acquis ; | B26: ="Q" & J26 & "!" & M26 -> Q13!D | C26: ="Q" & K26 & "!" & N26 -> Q14!D | D26: ="Q" & L26 & "!" & O26 -> Q15!D | E26: Gouvernance | J26: 13 | K26: 14 | L26: 15 | M26: D | N26: D | O26: D
A27: ce qui bloque l'étape suivante ; | B27: ="Q" & J27 & "!" & M27 -> Q13!E | C27: ="Q" & K27 & "!" & N27 -> Q14!E | D27: ="Q" & L27 & "!" & O27 -> Q15!E | J27: 13 | K27: 14 | L27: 15 | M27: E | N27: E | O27: E
A28: les capacités à construire ; | B28: ="Q" & J28 & "!" & M28 -> Q13!F | C28: ="Q" & K28 & "!" & N28 -> Q14!F | D28: ="Q" & L28 & "!" & O28 -> Q15!F | J28: 13 | K28: 14 | L28: 15 | M28: F | N28: F | O28: F
A29: les actions prioritaires ; | B29: ="Q" & J29 & "!" & M29 -> Q13!G | C29: ="Q" & K29 & "!" & N29 -> Q14!G | D29: ="Q" & L29 & "!" & O29 -> Q15!G | J29: 13 | K29: 14 | L29: 15 | M29: G | N29: G | O29: G
A30: les résultats attendus. | B30: ="Q" & J30 & "!" & M30 -> Q13!H | C30: ="Q" & K30 & "!" & N30 -> Q14!H | D30: ="Q" & L30 & "!" & O30 -> Q15!H | J30: 13 | K30: 14 | L30: 15 | M30: H | N30: H | O30: H

Sheet _tmp_export
A1: Potentiel | B1: 1
A2: Strategie | B2: 1
A3: Culture | B3: 1
A4: Competences | B4: 1
A5: Gouvernance | B5: 1

Sheet _tmp_export_103005
A1: Potentiel | B1: 1
A2: Strategie | B2: 1
A3: Culture | B3: 1
A4: Competences | B4: 1
A5: Gouvernance | B5: 1

Sheet _tmp_export_103300
A1: Potentiel | B1: 1
A2: Strategie | B2: 1
A3: Culture | B3: 1
A4: Competences | B4: 1
A5: Gouvernance | B5: 1

Sheet _tmp_export_103654
A1: Potentiel | B1: 1
A2: Strategie | B2: 1
A3: Culture | B3: 1
A4: Competences | B4: 1
A5: Gouvernance | B5: 1

Sheet _tmp_export_104038
A1: Potentiel | B1: 1
A2: Strategie | B2: 1
A3: Culture | B3: 1
A4: Competences | B4: 1
A5: Gouvernance | B5: 1

Sheet _tmp_export_162014
A1: Potentiel | B1: 1
A2: Strategie | B2: 1
A3: Culture | B3: 1
A4: Competences | B4: 1
A5: Gouvernance | B5: 1

Sheet _tmp_export_162057
A1: Potentiel | B1: 1
A2: Strategie | B2: 1
A3: Culture | B3: 1
A4: Competences | B4: 1
A5: Gouvernance | B5: 1

Sheet _tmp_export_162352
A1: Potentiel | B1: 1
A2: Strategie | B2: 1
A3: Culture | B3: 1
A4: Competences | B4: 1
A5: Gouvernance | B5: 1

Sheet _tmp_export_164730
A1: Potentiel | B1: 1
A2: Strategie | B2: 1
A3: Culture | B3: 1
A4: Competences | B4: 1
A5: Gouvernance | B5: 1

Sheet _tmp_export_164906
A1: Potentiel | B1: 1
A2: Strategie | B2: 1
A3: Culture | B3: 1
A4: Competences | B4: 1
A5: Gouvernance | B5: 1

Sheet MatriceEntreprise
B1: Potentiel | C1: Stratégie | D1: Culture | E1: Compétences | F1: Gouvernance | G1: moyenne | H1: EntrepriseE | I1: FORCE | J1: POINT DE VIGILANCE | K1: PLAN COURT TERME | L1: PLAN MOYEN TERME | O1: Émergence | P1: Structuration | Q1: Industrialisation | R1: moyenne | S1: TRI des 3 forces | T1: L | U1: C | W1: TRI des 3 vigilences | X1: L | Y1: C | AA1: moyen terme initial | AB1: S | AC1: L | AD1: C | AG1: S | AH1: L | AI1: C | AJ1: min existant | AL1: S | AM1: L | AN1: C | AO1: check
A2: Émergence | B2: {=INDIRECT("Réponses!C" & $H$2)} -> 0 | C2: {=INDIRECT("Réponses!F" & $H$2)} -> 0 | D2: {=INDIRECT("Réponses!I" & $H$2)} -> 0 | E2: {=INDIRECT("Réponses!L" & $H$2)} -> 0 | F2: {=INDIRECT("Réponses!O" & $H$2)} -> 0 | G2: =AVERAGE(B2:F2) -> 0 | H2: =MATCH(H1,Réponses!B1:B6) -> 6 | I2: =OFFSET(TMatrice!$Y$2,MatriceEntreprise!U2-1,MatriceEntreprise!T2-1) & S2 +5 -> Q01!D5 | J2: =OFFSET(TMatrice!$AJ$2,MatriceEntreprise!U2-1,MatriceEntreprise!T2-1) & W2 +5 -> Q01!E5 | K2: =OFFSET(TMatrice!$BF$2,MatriceEntreprise!U2-1,MatriceEntreprise!T2-1) & W2 +5 -> Q01!G5 | L2: =IF(AO12,"attention, revoir colonneAO","OK") -> OK | N2: Potentiel | O2: {=INDIRECT("Réponses!C" & $H$2)} -> 0 | P2: {=INDIRECT("Réponses!D" & $H$2)} -> 0 | Q2: {=INDIRECT("Réponses!E" & $H$2)} -> 0 | R2: =AVERAGE(O2:Q2) -> 0 | S2: {=_xlfn.LET(_xlpm.plage, B2:F4, _xlpm.lignes, ROW(_xlpm.plage) - ROW(B2) + 1, _xlpm.colonnes, COLUMN(_xlpm.plage) - COLUMN(B2) + 1, _xlpm.vals, _xlfn.TOCOL(_xlpm.plage), _xlpm.l_s, _xlfn.TOCOL(IF(_xlpm.plage<>"", _xlpm.lignes,"")), _xlpm.c_s, _xlfn.TOCOL(IF(_xlpm.plage<>"", _xlpm.colonnes,"")), _xlpm.trier, _xlfn._xlws.SORT(_xlfn.HSTACK(_xlpm.vals,_xlpm.l_s,_xlpm.c_s), 1, -1), _xlfn.CHOOSEROWS(_xlpm.trier, _xlfn.SEQUENCE(3)))} -> 0 | T2: 1 | U2: 1 | W2: {=_xlfn.LET(_xlpm.plage, B2:F4, _xlpm.lignes, ROW(_xlpm.plage) - ROW(B2) + 1, _xlpm.colonnes, COLUMN(_xlpm.plage) - COLUMN(B2) + 1, _xlpm.vals, _xlfn.TOCOL(_xlpm.plage), _xlpm.l_s, _xlfn.TOCOL(IF(_xlpm.plage<>"", _xlpm.lignes,"")), _xlpm.c_s, _xlfn.TOCOL(IF(_xlpm.plage<>"", _xlpm.colonnes,"")), _xlpm.trier, _xlfn._xlws.SORT(_xlfn.HSTACK(_xlpm.vals,_xlpm.l_s,_xlpm.c_s), 1, 1), _xlfn.CHOOSEROWS(_xlpm.trier, _xlfn.SEQUENCE(3)))} -> 0 | X2: 1 | Y2: 1 | AA2: Potentiel | AB2: {=_xlfn.LET(_xlpm.plage, B2:B4, _xlpm.lignes, ROW(_xlpm.plage) - ROW(B2) + 1, _xlpm.colonnes, COLUMN(_xlpm.plage) - COLUMN(B2) + 1, _xlpm.vals, _xlfn.TOCOL(_xlpm.plage), _xlpm.l_s, _xlfn.TOCOL(IF(_xlpm.plage<>"", _xlpm.lignes,"")), _xlpm.c_s, _xlfn.TOCOL(IF(_xlpm.plage<>"", _xlpm.colonnes,"")), _xlpm.trier, _xlfn._xlws.SORT(_xlfn.HSTACK(_xlpm.vals,_xlpm.l_s,_xlpm.c_s), 1, 1), _xlfn.CHOOSEROWS(_xlpm.trier, _xlfn.SEQUENCE(2)))} -> 0 | AC2: 1 | AD2: 1 | AE2: 1 | AG2: =AB2 -> 0 | AH2: =AC2 -> 1 | AI2: 1 | AJ2: {=MATCH(1, (W$2:W$4=AG2) * (X$2:X$4=AH2) * (Y$2:Y$4=AI2), 0)} -> 1 | AK2: =IF(ISERROR(AJ2),0,1) -> 1 | AL2: =IF(ISERROR($AJ2),AG2,IF(AG2<5,AG2+1,1)) -> 1 | AM2: =AH2 -> 1 | AN2: 1 | AO2: {=IF(ISERROR(MATCH(1, (W$2:W$4=AL2) * (X$2:X$4=AM2) * (Y$2:Y$4=AN2), 0)),0,1)} -> 0
A3: Structuration | B3: {=INDIRECT("Réponses!D" & $H$2)} -> 0 | C3: {=INDIRECT("Réponses!G" & $H$2)} -> 0 | D3: {=INDIRECT("Réponses!J" & $H$2)} -> 0 | E3: {=INDIRECT("Réponses!M" & $H$2)} -> 0 | F3: {=INDIRECT("Réponses!P" & $H$2)} -> 0 | G3: =AVERAGE(B3:F3) -> 0 | I3: =OFFSET(TMatrice!$Y$2,MatriceEntreprise!U3-1,MatriceEntreprise!T3-1) & S3 +5 -> Q04!D5 | J3: =OFFSET(TMatrice!$AJ$2,MatriceEntreprise!U3-1,MatriceEntreprise!T3-1) & W3 +5 -> Q04!E5 | K3: =OFFSET(TMatrice!$BF$2,MatriceEntreprise!U3-1,MatriceEntreprise!T3-1) & W3 +5 -> Q04!G5 | N3: Stratégie | O3: {=INDIRECT("Réponses!F" & $H$2)} -> 0 | P3: {=INDIRECT("Réponses!G" & $H$2)} -> 0 | Q3: {=INDIRECT("Réponses!H" & $H$2)} -> 0 | R3: =AVERAGE(O3:Q3) -> 0 | S3: 0 | T3: 1 | U3: 2 | W3: 0 | X3: 1 | Y3: 2 | AB3: 0 | AC3: 2 | AD3: 1 | AE3: 1 | AG3: =AB3 -> 0 | AH3: =AC3 -> 2 | AI3: 1 | AJ3: {=MATCH(1, (W$2:W$4=AG3) * (X$2:X$4=AH3) * (Y$2:Y$4=AI3), 0)} -> #N/A | AK3: =IF(ISERROR(AJ3),0,1) -> 0 | AL3: =IF(ISERROR($AJ3),AG3,IF(AG3<5,AG3+1,1)) -> 0 | AM3: =AH3 -> 2 | AN3: 1 | AO3: {=IF(ISERROR(MATCH(1, (W$2:W$4=AL3) * (X$2:X$4=AM3) * (Y$2:Y$4=AN3), 0)),0,1)} -> 0
A4: Industrialisation | B4: {=INDIRECT("Réponses!E" & $H$2)} -> 0 | C4: {=INDIRECT("Réponses!H" & $H$2)} -> 0 | D4: {=INDIRECT("Réponses!K" & $H$2)} -> 0 | E4: {=INDIRECT("Réponses!N" & $H$2)} -> 0 | F4: {=INDIRECT("Réponses!Q" & $H$2)} -> 0 | G4: =AVERAGE(B4:F4) -> 0 | I4: =OFFSET(TMatrice!$Y$2,MatriceEntreprise!U4-1,MatriceEntreprise!T4-1) & S4 +5 -> Q07!D5 | J4: =OFFSET(TMatrice!$AJ$2,MatriceEntreprise!U4-1,MatriceEntreprise!T4-1) & W4 +5 -> Q07!E5 | K4: =OFFSET(TMatrice!$BF$2,MatriceEntreprise!U4-1,MatriceEntreprise!T4-1) & W4 +5 -> Q07!G5 | N4: Culture | O4: {=INDIRECT("Réponses!I" & $H$2)} -> 0 | P4: {=INDIRECT("Réponses!J" & $H$2)} -> 0 | Q4: {=INDIRECT("Réponses!K" & $H$2)} -> 0 | R4: =AVERAGE(O4:Q4) -> 0 | S4: 0 | T4: 1 | U4: 3 | W4: 0 | X4: 1 | Y4: 3 | AA4: Stratégie | AB4: {=_xlfn.LET(_xlpm.plage, C2:C4, _xlpm.lignes, ROW(_xlpm.plage) - ROW(C2) + 1, _xlpm.colonnes, COLUMN(_xlpm.plage) - COLUMN(C2) + 1, _xlpm.vals, _xlfn.TOCOL(_xlpm.plage), _xlpm.l_s, _xlfn.TOCOL(IF(_xlpm.plage<>"", _xlpm.lignes,"")), _xlpm.c_s, _xlfn.TOCOL(IF(_xlpm.plage<>"", _xlpm.colonnes,"")), _xlpm.trier, _xlfn._xlws.SORT(_xlfn.HSTACK(_xlpm.vals,_xlpm.l_s,_xlpm.c_s), 1, 1), _xlfn.CHOOSEROWS(_xlpm.trier, _xlfn.SEQUENCE(2)))} -> 0 | AC4: 1 | AD4: 1 | AE4: 2 | AG4: =AB4 -> 0 | AH4: =AC4 -> 1 | AI4: 2 | AJ4: {=MATCH(1, (W$2:W$4=AG4) * (X$2:X$4=AH4) * (Y$2:Y$4=AI4), 0)} -> 2 | AK4: =IF(ISERROR(AJ4),0,1) -> 1 | AL4: =IF(ISERROR($AJ4),AG4,IF(AG4<5,AG4+1,1)) -> 1 | AM4: =AH4 -> 1 | AN4: 2 | AO4: {=IF(ISERROR(MATCH(1, (W$2:W$4=AL4) * (X$2:X$4=AM4) * (Y$2:Y$4=AN4), 0)),0,1)} -> 0
A5: moyenne | B5: =AVERAGE(B2:B4) -> 0 | C5: =AVERAGE(C2:C4) -> 0 | D5: =AVERAGE(D2:D4) -> 0 | E5: =AVERAGE(E2:E4) -> 0 | F5: =AVERAGE(F2:F4) -> 0 | G5: =AVERAGE(G2:G4) -> 0 | N5: Compétences | O5: {=INDIRECT("Réponses!L" & $H$2)} -> 0 | P5: {=INDIRECT("Réponses!M" & $H$2)} -> 0 | Q5: {=INDIRECT("Réponses!N" & $H$2)} -> 0 | R5: =AVERAGE(O5:Q5) -> 0 | AB5: 0 | AC5: 2 | AD5: 1 | AE5: 2 | AG5: =AB5 -> 0 | AH5: =AC5 -> 2 | AI5: 2 | AJ5: {=MATCH(1, (W$2:W$4=AG5) * (X$2:X$4=AH5) * (Y$2:Y$4=AI5), 0)} -> #N/A | AK5: =IF(ISERROR(AJ5),0,1) -> 0 | AL5: =IF(ISERROR($AJ5),AG5,IF(AG5<5,AG5+1,1)) -> 0 | AM5: =AH5 -> 2 | AN5: 2 | AO5: {=IF(ISERROR(MATCH(1, (W$2:W$4=AL5) * (X$2:X$4=AM5) * (Y$2:Y$4=AN5), 0)),0,1)} -> 0
N6: Gouvernance | O6: {=INDIRECT("Réponses!O" & $H$2)} -> 0 | P6: {=INDIRECT("Réponses!P" & $H$2)} -> 0 | Q6: {=INDIRECT("Réponses!Q" & $H$2)} -> 0 | R6: =AVERAGE(O6:Q6) -> 0 | AA6: Culture | AB6: {=_xlfn.LET(_xlpm.plage, D2:D4, _xlpm.lignes, ROW(_xlpm.plage) - ROW(D2) + 1, _xlpm.colonnes, COLUMN(_xlpm.plage) - COLUMN(D2) + 1, _xlpm.vals, _xlfn.TOCOL(_xlpm.plage), _xlpm.l_s, _xlfn.TOCOL(IF(_xlpm.plage<>"", _xlpm.lignes,"")), _xlpm.c_s, _xlfn.TOCOL(IF(_xlpm.plage<>"", _xlpm.colonnes,"")), _xlpm.trier, _xlfn._xlws.SORT(_xlfn.HSTACK(_xlpm.vals,_xlpm.l_s,_xlpm.c_s), 1, 1), _xlfn.CHOOSEROWS(_xlpm.trier, _xlfn.SEQUENCE(2)))} -> 0 | AC6: 1 | AD6: 1 | AE6: 3 | AG6: =AB6 -> 0 | AH6: =AC6 -> 1 | AI6: 3 | AJ6: {=MATCH(1, (W$2:W$4=AG6) * (X$2:X$4=AH6) * (Y$2:Y$4=AI6), 0)} -> 3 | AK6: =IF(ISERROR(AJ6),0,1) -> 1 | AL6: =IF(ISERROR($AJ6),AG6,IF(AG6<5,AG6+1,1)) -> 1 | AM6: =AH6 -> 1 | AN6: 3 | AO6: {=IF(ISERROR(MATCH(1, (W$2:W$4=AL6) * (X$2:X$4=AM6) * (Y$2:Y$4=AN6), 0)),0,1)} -> 0
N7: moyenne | O7: =AVERAGE(O2:O6) -> 0 | P7: =AVERAGE(P2:P6) -> 0 | Q7: =AVERAGE(Q2:Q6) -> 0 | R7: =AVERAGE(R2:R6) -> 0 | AB7: 0 | AC7: 2 | AD7: 1 | AE7: 3 | AG7: =AB7 -> 0 | AH7: =AC7 -> 2 | AI7: 3 | AJ7: {=MATCH(1, (W$2:W$4=AG7) * (X$2:X$4=AH7) * (Y$2:Y$4=AI7), 0)} -> #N/A | AK7: =IF(ISERROR(AJ7),0,1) -> 0 | AL7: =IF(ISERROR($AJ7),AG7,IF(AG7<5,AG7+1,1)) -> 0 | AM7: =AH7 -> 2 | AN7: 3 | AO7: {=IF(ISERROR(MATCH(1, (W$2:W$4=AL7) * (X$2:X$4=AM7) * (Y$2:Y$4=AN7), 0)),0,1)} -> 0
AA8: Compétences | AB8: {=_xlfn.LET(_xlpm.plage, E2:E4, _xlpm.lignes, ROW(_xlpm.plage) - ROW(E2) + 1, _xlpm.colonnes, COLUMN(_xlpm.plage) - COLUMN(E2) + 1, _xlpm.vals, _xlfn.TOCOL(_xlpm.plage), _xlpm.l_s, _xlfn.TOCOL(IF(_xlpm.plage<>"", _xlpm.lignes,"")), _xlpm.c_s, _xlfn.TOCOL(IF(_xlpm.plage<>"", _xlpm.colonnes,"")), _xlpm.trier, _xlfn._xlws.SORT(_xlfn.HSTACK(_xlpm.vals,_xlpm.l_s,_xlpm.c_s), 1, 1), _xlfn.CHOOSEROWS(_xlpm.trier, _xlfn.SEQUENCE(2)))} -> 0 | AC8: 1 | AD8: 1 | AE8: 4 | AG8: =AB8 -> 0 | AH8: =AC8 -> 1 | AI8: 4 | AJ8: {=MATCH(1, (W$2:W$4=AG8) * (X$2:X$4=AH8) * (Y$2:Y$4=AI8), 0)} -> #N/A | AK8: =IF(ISERROR(AJ8),0,1) -> 0 | AL8: =IF(ISERROR($AJ8),AG8,IF(AG8<5,AG8+1,1)) -> 0 | AM8: =AH8 -> 1 | AN8: 4 | AO8: {=IF(ISERROR(MATCH(1, (W$2:W$4=AL8) * (X$2:X$4=AM8) * (Y$2:Y$4=AN8), 0)),0,1)} -> 0
AB9: 0 | AC9: 2 | AD9: 1 | AE9: 4 | AG9: =AB9 -> 0 | AH9: =AC9 -> 2 | AI9: 4 | AJ9: {=MATCH(1, (W$2:W$4=AG9) * (X$2:X$4=AH9) * (Y$2:Y$4=AI9), 0)} -> #N/A | AK9: =IF(ISERROR(AJ9),0,1) -> 0 | AL9: =IF(ISERROR($AJ9),AG9,IF(AG9<5,AG9+1,1)) -> 0 | AM9: =AH9 -> 2 | AN9: 4 | AO9: {=IF(ISERROR(MATCH(1, (W$2:W$4=AL9) * (X$2:X$4=AM9) * (Y$2:Y$4=AN9), 0)),0,1)} -> 0
AA10: Gouvernance | AB10: {=_xlfn.LET(_xlpm.plage, F2:F4, _xlpm.lignes, ROW(_xlpm.plage) - ROW(F2) + 1, _xlpm.colonnes, COLUMN(_xlpm.plage) - COLUMN(F2) + 1, _xlpm.vals, _xlfn.TOCOL(_xlpm.plage), _xlpm.l_s, _xlfn.TOCOL(IF(_xlpm.plage<>"", _xlpm.lignes,"")), _xlpm.c_s, _xlfn.TOCOL(IF(_xlpm.plage<>"", _xlpm.colonnes,"")), _xlpm.trier, _xlfn._xlws.SORT(_xlfn.HSTACK(_xlpm.vals,_xlpm.l_s,_xlpm.c_s), 1, 1), _xlfn.CHOOSEROWS(_xlpm.trier, _xlfn.SEQUENCE(2)))} -> 0 | AC10: 1 | AD10: 1 | AE10: 5 | AG10: =AB10 -> 0 | AH10: =AC10 -> 1 | AI10: 5 | AJ10: {=MATCH(1, (W$2:W$4=AG10) * (X$2:X$4=AH10) * (Y$2:Y$4=AI10), 0)} -> #N/A | AK10: =IF(ISERROR(AJ10),0,1) -> 0 | AL10: =IF(ISERROR($AJ10),AG10,IF(AG10<5,AG10+1,1)) -> 0 | AM10: =AH10 -> 1 | AN10: 5 | AO10: {=IF(ISERROR(MATCH(1, (W$2:W$4=AL10) * (X$2:X$4=AM10) * (Y$2:Y$4=AN10), 0)),0,1)} -> 0
AB11: 0 | AC11: 2 | AD11: 1 | AE11: 5 | AG11: =AB11 -> 0 | AH11: =AC11 -> 2 | AI11: 5 | AJ11: {=MATCH(1, (W$2:W$4=AG11) * (X$2:X$4=AH11) * (Y$2:Y$4=AI11), 0)} -> #N/A | AK11: =IF(ISERROR(AJ11),0,1) -> 0 | AL11: =IF(ISERROR($AJ11),AG11,IF(AG11<5,AG11+1,1)) -> 0 | AM11: =AH11 -> 2 | AN11: 5 | AO11: {=IF(ISERROR(MATCH(1, (W$2:W$4=AL11) * (X$2:X$4=AM11) * (Y$2:Y$4=AN11), 0)),0,1)} -> 0
F12: La roadmap est ensuite construite en identifiant : | H12: Potentiel | I12: Stratégie | J12: Culture | K12: Compétences | L12: Gouvernance | AK12: =SUM(AK2:AK11) -> 3 | AO12: =SUM(AO2:AO11) -> 0
F13: ce qui est déjà acquis | H13: =_xlfn.CONCAT(INDIRECT(TMatrice!$B2 & (B$2+5))," ",INDIRECT(TMatrice!$C2 & (B$3+5))," ",INDIRECT(TMatrice!$D2 & (B$4+5))) -> Rien n'est acquis. Aucune donnée pertinente identifiée. Aucun cas d'usage pertinent. | I13: =_xlfn.CONCAT(INDIRECT(TMatrice!$B8 & (C$2+5))," ",INDIRECT(TMatrice!$C8 & (C$3+5))," ",INDIRECT(TMatrice!$D8 & (C$4+5))) -> Aucune ambition. Aucune trajectoire. Aucun cas d'usage. | J13: =_xlfn.CONCAT(INDIRECT(TMatrice!$B14 & (D$2+5))," ",INDIRECT(TMatrice!$C14 & (D$3+5))," ",INDIRECT(TMatrice!$D14 & (D$4+5))) -> Absence d'implication Pas d'implication réelle. Il n'y a aucun dispositif d'apprentissage au sein de l'entreprise, d'expérimentation ou de partage autour de l'IA. | K13: =_xlfn.CONCAT(INDIRECT(TMatrice!$B20 & (E$2+5))," ",INDIRECT(TMatrice!$C20 & (E$3+5))," ",INDIRECT(TMatrice!$D20 & (E$4+5))) -> L'entreprise ne dispose pas de compétences internes identifiées en IA. Aucun dispositif de développement des compétences IA. L'entreprise n'a pas les capacité d'identifier les besoins et lacunes en compétences IA et aucun recours externe n'est organisé. | L13: =_xlfn.CONCAT(INDIRECT(TMatrice!$B26 & (F$2+5))," ",INDIRECT(TMatrice!$C26 & (F$3+5))," ",INDIRECT(TMatrice!$D26 & (F$4+5))) -> L'entreprise n'a aucun principe, règle ou responsabilité n'est défini pour l'utilisation de l'IA. Au sein de l'entreprise, les solutions IA peuvent être déployées sans processus d'évaluation ou de validation. L'entreprise n'a pas mis en place de suivit des solutions IA après leur déploiement.
F14: ce qui bloque l'étape suivante | H14: =_xlfn.CONCAT(INDIRECT(TMatrice!$B3 & (B$2+5))," ",INDIRECT(TMatrice!$C3 & (B$3+5))," ",INDIRECT(TMatrice!$D3 & (B$4+5))) -> L'entreprise n'a pas de moyens techniques pour permettre l'expérimentation de solutions IA. L'entreprise n'a pas identifié les 1ères données à exploiter même si elles sont dispersées. Absence d'identification de cas d'usage IA | I14: =_xlfn.CONCAT(INDIRECT(TMatrice!$B9 & (C$2+5))," ",INDIRECT(TMatrice!$C9 & (C$3+5))," ",INDIRECT(TMatrice!$D9 & (C$4+5))) -> L'IA absente des réflexions stratégiques de l'entreprise. Absence d'actions coordonnées pour structurer la feuille de route IA. L'entreprise n'a pas identifié de cas d'usage permettant un début de gestion de portefeuille projet IA. | J14: =_xlfn.CONCAT(INDIRECT(TMatrice!$B15 & (D$2+5))," ",INDIRECT(TMatrice!$C15 & (D$3+5))," ",INDIRECT(TMatrice!$D15 & (D$4+5))) -> Les managers ne sont pas sensibilisés à l'IA Manque de confiance et de légitimité managériale provoquant une forte résistance sur la mise en place de l'IA au sein de l'entreprise. Il n'y a pas de dispositifs d'apprentissage informels de l'IA en entreprise. | K14: =_xlfn.CONCAT(INDIRECT(TMatrice!$B21 & (E$2+5))," ",INDIRECT(TMatrice!$C21 & (E$3+5))," ",INDIRECT(TMatrice!$D21 & (E$4+5))) -> L'entreprise ne dispose pas de compétences internes identifiées en IA. Elle peut avoir une dépendance totale à l'extérieur. L'entreprise n'a aucun dispositif permettant d'envisager une progression des compétences en IA. L'entreprise n'a pas de mécanisme d'identification au cas par cas des lacunes dans les compétences IA de ses équipes. | L14: =_xlfn.CONCAT(INDIRECT(TMatrice!$B27 & (F$2+5))," ",INDIRECT(TMatrice!$C27 & (F$3+5))," ",INDIRECT(TMatrice!$D27 & (F$4+5))) -> L'entreprise manque de cadrage informel pour commencer à définir certaines taches et responsabilités pour l'utilisation de l'IA. L'entreprise ne controle pas les déploiements des projets et usages IA. Le fonctionnement des solutions IA n'est pas vérifié ponctuellement, généralement en cas de problème et des dérive non détectées sont possibles.
F15: les capacités à construire | H15: =_xlfn.CONCAT(INDIRECT(TMatrice!$B4 & (B$2+5))," ",INDIRECT(TMatrice!$C4 & (B$3+5))," ",INDIRECT(TMatrice!$D4 & (B$4+5))) -> Acquérir la capacité à disposer d’un socle technologique permettant de développer et déployer des solutions d’IA. Acquérir la capacité à identifier (inventaire) et rendre disponibles les données pertinentes pour les usages d’IA. Acquérir la capacité à identifier les opportunités dans lesquelles l’IA pourrait présenter un cas d’usage pertinent. | I15: =_xlfn.CONCAT(INDIRECT(TMatrice!$B10 & (C$2+5))," ",INDIRECT(TMatrice!$C10 & (C$3+5))," ",INDIRECT(TMatrice!$D10 & (C$4+5))) -> Acquérir la capacité à intégrer l’IA dans les réflexions et ambitions de l’entreprise auprès des managers. Acquérir la capacité à définir une première trajectoire d’actions permettant de mettre en œuvre l’ambition IA. Acquérir la capacité à identifier des cas d’usage IA répondant aux enjeux de l’entreprise. | J15: =_xlfn.CONCAT(INDIRECT(TMatrice!$B16 & (D$2+5))," ",INDIRECT(TMatrice!$C16 & (D$3+5))," ",INDIRECT(TMatrice!$D16 & (D$4+5))) -> Acquérir la capacité du leadership à comprendre les enjeux de l’IA et à identifier les premières opportunités d’utilisation dans l’entreprise. Acquérir la capacité à créer les conditions permettant aux collaborateurs d’accepter progressivement l’utilisation de l’IA. Acquérir la capacité à mettre en place un premier dispositif d’apprentissage et d’expérimentation. | K15: =_xlfn.CONCAT(INDIRECT(TMatrice!$B22 & (E$2+5))," ",INDIRECT(TMatrice!$C22 & (E$3+5))," ",INDIRECT(TMatrice!$D22 & (E$4+5))) -> Acquérir une première capacité interne à concevoir, développer, déployer ou exploiter des solutions d’IA. Acquérir la capacité à mettre en place un premier dispositif de développement des compétences IA des collaborateurs. Acquérir la capacité à identifier les besoins et lacunes en compétences et à les faire porter en externe. | L15: =_xlfn.CONCAT(INDIRECT(TMatrice!$B28 & (F$2+5))," ",INDIRECT(TMatrice!$C28 & (F$3+5))," ",INDIRECT(TMatrice!$D28 & (F$4+5))) -> Acquérir la capacité à définir les premiers principes de la gouvernance IA avec des règles et responsabilités encadrant l’utilisation de l’IA. Acquérir la capacité à évaluer et valider certaines solutions IA avant leur mise en production. Acquérir la capacité à suivre les solutions IA ponctuellement après leur déploiement.
F16: les actions prioritaires | H16: =_xlfn.CONCAT(INDIRECT(TMatrice!$B5 & (B$2+5))," ",INDIRECT(TMatrice!$C5 & (B$3+5))," ",INDIRECT(TMatrice!$D5 & (B$4+5))) -> Recenser les besoins minimaux en calcul, stockage et environnements ; définir une architecture initiale et les moyens IT/cloud mobilisables. Identifier des sources pertinentes, leurs propriétaires et les règles d’accès ; définir les premières règles de qualité. Identifier les activités et processus susceptibles de bénéficier de l’IA ; recueillir les besoins métiers et documenter les opportunités. | I16: =_xlfn.CONCAT(INDIRECT(TMatrice!$B11 & (C$2+5))," ",INDIRECT(TMatrice!$C11 & (C$3+5))," ",INDIRECT(TMatrice!$D11 & (C$4+5))) -> Sensibiliser les dirigeants aux possibilités et enjeux de l’IA ; organiser une première réflexion sur les ambitions possibles. Recenser initiatives et besoins IA ; définir premières étapes, responsables et échéances ; formaliser une trajectoire initiale. Recenser les premiers cas d’usage IA en lien avec les enjeux métiers ; documenter opportunités et besoins. | J16: =_xlfn.CONCAT(INDIRECT(TMatrice!$B17 & (D$2+5))," ",INDIRECT(TMatrice!$C17 & (D$3+5))," ",INDIRECT(TMatrice!$D17 & (D$4+5))) -> Sensibiliser dirigeants et managers aux enjeux IA ; identifier les premiers sponsors et clarifier leur rôle. Expliquer enjeux et bénéfices ; partager la vision entreprise sur l'IA. Identifier les besoins d’apprentissage et d’expérimentation ; mettre en place un premier dispositif de sensibilisation et de partage. | K16: =_xlfn.CONCAT(INDIRECT(TMatrice!$B23 & (E$2+5))," ",INDIRECT(TMatrice!$C23 & (E$3+5))," ",INDIRECT(TMatrice!$D23 & (E$4+5))) -> Identifier les compétences IA nécessaires ; recenser les compétences existantes et els personnes cibles ; définir les besoins de développement ou recrutement. Identifier populations et compétences prioritaires ; définir un premier dispositif de sensibilisation et de développement. Identifier besoins critiques ; cartographier lacunes ; définir les premiers moyens internes ou externes pour les combler. | L16: =_xlfn.CONCAT(INDIRECT(TMatrice!$B29 & (F$2+5))," ",INDIRECT(TMatrice!$C29 & (F$3+5))," ",INDIRECT(TMatrice!$D29 & (F$4+5))) -> Identifier les principaux risques et besoins de contrôle liés aux usages de l'IA ; définir premières règles et responsabilités ; sensibiliser les équipes. Définir des critères minimaux ; identifier les projets soumis à validation ; formaliser une première revue avant mise en production. Identifier les solutions IA en exploitation ; définir indicateurs et responsabilités ; mettre en place un premier contrôle post-déploiement.
F17: les résultats attendus | H17: =_xlfn.CONCAT(INDIRECT(TMatrice!$B6 & (B$2+5))," ",INDIRECT(TMatrice!$C6 & (B$3+5))," ",INDIRECT(TMatrice!$D6 & (B$4+5))) -> Une infrastructure minimale est disponible pour lancer les premiers projets IA. Les données pertinentes pour les premiers usages IA sont identifiées et accessibles. Un premier ensemble de cas d’usage IA pertinents est identifié. | I17: =_xlfn.CONCAT(INDIRECT(TMatrice!$B12 & (C$2+5))," ",INDIRECT(TMatrice!$C12 & (C$3+5))," ",INDIRECT(TMatrice!$D12 & (C$4+5))) -> L’IA est intégrée aux réflexions de l’entreprise et une première ambition est exprimée. Une première trajectoire IA existe avec actions et responsabilités identifiées. Un portefeuille initial de cas d’usage IA est identifié. | J17: =_xlfn.CONCAT(INDIRECT(TMatrice!$B18 & (D$2+5))," ",INDIRECT(TMatrice!$C18 & (D$3+5))," ",INDIRECT(TMatrice!$D18 & (D$4+5))) -> Les premiers sponsors comprennent les enjeux IA et commencent à soutenir le sujet. Les résistances sont identifiées et les collaborateurs disposent de premiers repères pour envisager l’IA. Un premier dispositif permet de découvrir, expérimenter et échanger autour de l’IA. | K17: =_xlfn.CONCAT(INDIRECT(TMatrice!$B24 & (E$2+5))," ",INDIRECT(TMatrice!$C24 & (E$3+5))," ",INDIRECT(TMatrice!$D24 & (E$4+5))) -> Les compétences IA prioritaires et les premiers moyens pour les acquérir sont identifiés. Un dispositif initial de développement des compétences IA est défini. Les principales lacunes sont identifiées et font l’objet d’un premier plan de traitement. | L17: =_xlfn.CONCAT(INDIRECT(TMatrice!$B30 & (F$2+5))," ",INDIRECT(TMatrice!$C30 & (F$3+5))," ",INDIRECT(TMatrice!$D30 & (F$4+5))) -> Un premier cadre de principes, règles et responsabilités encadre les usages IA prioritaires. Les projets IA font l’objet d’une première évaluation avant déploiement. Les solutions IA déployées sont identifiées et font l’objet d’un premier suivi.
G19: 3 forces | H19: =OFFSET($A$1,0,U2) & " - " & OFFSET($A$1,T2,0) -> Potentiel - Émergence | I19: {=INDIRECT(I2)} -> Rien n'est acquis.
H20: =OFFSET($A$1,0,U3) & " - " & OFFSET($A$1,T3,0) -> Stratégie - Émergence | I20: {=INDIRECT(I3)} -> Aucune ambition.
H21: =OFFSET($A$1,0,U4) & " - " & OFFSET($A$1,T4,0) -> Culture - Émergence | I21: {=INDIRECT(I4)} -> Absence d'implication
G23: 3 vigilences | H23: =OFFSET($A$1,0,Y2) & " - " & OFFSET($A$1,X2,0) -> Potentiel - Émergence | I23: {=INDIRECT(J2)} -> L'entreprise n'a pas de moyens techniques pour permettre l'expérimentation de solutions IA.
H24: =OFFSET($A$1,0,Y3) & " - " & OFFSET($A$1,X3,0) -> Stratégie - Émergence | I24: {=INDIRECT(J3)} -> L'IA absente des réflexions stratégiques de l'entreprise.
H25: =OFFSET($A$1,0,Y4) & " - " & OFFSET($A$1,X4,0) -> Culture - Émergence | I25: {=INDIRECT(J4)} -> Les managers ne sont pas sensibilisés à l'IA
G27: plan d'actions cout terme | H27: =OFFSET($A$1,0,Y2) & " - " & OFFSET($A$1,X2,0) -> Potentiel - Émergence | I27: {=INDIRECT(K2)} -> Recenser les besoins minimaux en calcul, stockage et environnements ; définir une architecture initiale et les moyens IT/cloud mobilisables.
H28: =OFFSET($A$1,0,Y3) & " - " & OFFSET($A$1,X3,0) -> Stratégie - Émergence | I28: {=INDIRECT(K3)} -> Sensibiliser les dirigeants aux possibilités et enjeux de l’IA ; organiser une première réflexion sur les ambitions possibles.
H29: =OFFSET($A$1,0,Y4) & " - " & OFFSET($A$1,X4,0) -> Culture - Émergence | I29: {=INDIRECT(K4)} -> Sensibiliser dirigeants et managers aux enjeux IA ; identifier les premiers sponsors et clarifier leur rôle.
G31: plan d'actions moyen terme | H31: Potentiel | I31: {=CHAR(10) & "a. " & INDIRECT(OFFSET(TMatrice!$BF$2,MatriceEntreprise!AM2-1,MatriceEntreprise!AD2-1) & AL2 +5) & CHAR(10) & "b. " & INDIRECT(OFFSET(TMatrice!$BF$2,MatriceEntreprise!AM3-1,MatriceEntreprise!AD3-1) & AL3 +5)} -> a. Mettre en place un environnement d’expérimentation dédié à l'IA ; définir des configurations reproductibles et les modalités d’accès aux ressources. b. Sensibiliser les dirigeants aux possibilités et enjeux de l’IA ; organiser une première réflexion sur les ambitions possibles.
H33: Stratégie | I33: {=CHAR(10) & "a. " & INDIRECT(OFFSET(TMatrice!$BF$2,MatriceEntreprise!AM4-1,MatriceEntreprise!AD4-1) & AL4 +5) & CHAR(10) & "b. " & INDIRECT(OFFSET(TMatrice!$BF$2,MatriceEntreprise!AM5-1,MatriceEntreprise!AD5-1) & AL5 +5)} -> a. Mettre en place un environnement d’expérimentation dédié à l'IA ; définir des configurations reproductibles et les modalités d’accès aux ressources. b. Sensibiliser les dirigeants aux possibilités et enjeux de l’IA ; organiser une première réflexion sur les ambitions possibles.
H35: Culture | I35: {=CHAR(10) & "a. " & INDIRECT(OFFSET(TMatrice!$BF$2,MatriceEntreprise!AM6-1,MatriceEntreprise!AD6-1) & AL6 +5) & CHAR(10) & "b. " & INDIRECT(OFFSET(TMatrice!$BF$2,MatriceEntreprise!AM7-1,MatriceEntreprise!AD7-1) & AL7 +5)} -> a. Mettre en place un environnement d’expérimentation dédié à l'IA ; définir des configurations reproductibles et les modalités d’accès aux ressources. b. Sensibiliser les dirigeants aux possibilités et enjeux de l’IA ; organiser une première réflexion sur les ambitions possibles.
H37: Compétences | I37: {=CHAR(10) & "a. " & INDIRECT(OFFSET(TMatrice!$BF$2,MatriceEntreprise!AM8-1,MatriceEntreprise!AD8-1) & AL8 +5) & CHAR(10) & "b. " & INDIRECT(OFFSET(TMatrice!$BF$2,MatriceEntreprise!AM9-1,MatriceEntreprise!AD9-1) & AL9 +5)} -> a. Recenser les besoins minimaux en calcul, stockage et environnements ; définir une architecture initiale et les moyens IT/cloud mobilisables. b. Sensibiliser les dirigeants aux possibilités et enjeux de l’IA ; organiser une première réflexion sur les ambitions possibles.
H39: Gouvernance | I39: {=CHAR(10) & "a. " & INDIRECT(OFFSET(TMatrice!$BF$2,MatriceEntreprise!AM10-1,MatriceEntreprise!AD10-1) & AL10 +5) & CHAR(10) & "b. " & INDIRECT(OFFSET(TMatrice!$BF$2,MatriceEntreprise!AM11-1,MatriceEntreprise!AD11-1) & AL11 +5)} -> a. Recenser les besoins minimaux en calcul, stockage et environnements ; définir une architecture initiale et les moyens IT/cloud mobilisables. b. Sensibiliser les dirigeants aux possibilités et enjeux de l’IA ; organiser une première réflexion sur les ambitions possibles.

Sheet Q01
A1: {=INDIRECT("IndexQuestions!A" & (A2+3)) & " - " & INDIRECT("IndexQuestions!B" & (A2+3)) & " - " & INDIRECT("IndexQuestions!C" & (A2+3)) & " - " & INDIRECT("IndexQuestions!D" & (A2+3))} -> Q01 - POTENTIEL - Emergence - Soutien à l'IA
A2: {=RIGHT(CELL("nomfichier",A3),2)} -> 01 | B2: {=INDIRECT("IndexQuestions!E" & (A2+3))} -> Quelles sont les infrastructures technologiques en place pour soutenir des projets d’IA ?
A3: Logique | B3: À chaque score : acquis → blocage vers le niveau suivant → capacité à acquérir → actions prioritaires → résultat attendu.
A4: Score | B4: Thème | C4: Réponse | D4: Ce qui est déjà acquis | E4: Ce qui bloque l’étape suivante | F4: Capacités à acquérir | G4: Actions prioritaires | H4: Résultats attendus
A5: 0 | B5: Absente | C5: Aucune infrastructure ou capacité spécifique permettant de développer ou déployer des solutions IA. | D5: Rien n'est acquis. | E5: L'entreprise n'a pas de moyens techniques pour permettre l'expérimentation de solutions IA. | F5: Acquérir la capacité à disposer d’un socle technologique permettant de développer et déployer des solutions d’IA. | G5: Recenser les besoins minimaux en calcul, stockage et environnements ; définir une architecture initiale et les moyens IT/cloud mobilisables. | H5: Une infrastructure minimale est disponible pour lancer les premiers projets IA.
A6: 1 | B6: Expérimentale | C6: Des ressources IT/cloud existantes sont utilisées ponctuellement pour des expérimentations IA. | D6: L'entreprise à mis en place des ressources IT/cloud pour des expérimentations. | E6: L'entreprise manque d'environnements dédiés pour quelques projets sans viser une forte reproductibilité. | F6: Acquérir la capacité à utiliser de manière reproductible des environnements IA pour expérimenter l’IA. | G6: Mettre en place un environnement d’expérimentation dédié à l'IA ; définir des configurations reproductibles et les modalités d’accès aux ressources. | H6: Les expérimentations IA peuvent être réalisées de façon reproductible dans des environnements partagés.
A7: 2 | B7: Disponible | C7: Une infrastructure dédiée permettant de réaliser des projets IA existe, mais elle reste limitée, hétérogène ou peu standardisée. | D7: L'entreprise dispose d'une infrastructure pour quelques projets. | E7: Le manque de structuration et de standards limite le passage à une début d'industrialisation des projets IA | F7: Acquérir une plateforme IA suffisamment standardisée pour soutenir différents projets. | G7: Définir une architecture IA cible ; standardiser les environnements de développement et de déploiement et les capacités de calcul. | H7: Les équipes disposent d’environnements IA dédiés pour plusieurs projets.
A8: 3 | B8: Standardisée | C8: Des environnements dédiés à l'IA sont standardisés, avec des capacités de calcul adaptées et des processus structurés de développement et de déploiement. | D8: Des environnements dédiés et processus standardisés sont acquis au sein de l'entreprise | E8: L'insuffisance d'automatisation, de monitoring et d'optimisation des environnement IA freinant le renforcement la performance des infrastructure. | F8: Acquérir des environnements IA dédiés avec des capacités de calcul adaptées et des processus structurés de développement et de déploiement (MLOps/LLMOps). | G8: Automatiser la mise à disposition des environnements ; industrialiser développement et déploiement ; renforcer sécurité et gestion des accès. | H8: Les projets IA peuvent être développés et déployés dans des environnements industrialisés et sécurisés.
A9: 4 | B9: Optimisée | C9: L'infrastructure est scalable, automatisée, sécurisée et optimisée pour les performances et les coûts des workloads IA. | D9: L'entreprise a acquis des composants scalables, automatisés et sécurisés, permettant l'optimisation des ressources IA | E9: Le manque d'une gouvernance permettant la mutualisation et la gestion multi-usages pour renforcer la présence de l'IA comme asset industriel. | F9: Acquérir la capacité à faire évoluer, automatiser, sécuriser et optimiser l’infrastructure IA de l'entreprise en fonction des performances et des coûts. | G9: Piloter performances et coûts ; automatiser le dimensionnement ; renforcer supervision, sécurité et optimisation des ressources. | H9: L’infrastructure IA s’adapte aux besoins avec performances maîtrisées, sécurité suivie et coûts optimisés.
A10: 5 | B10: À l'échelle de l'entreprise | C10: Une plateforme IA gouvernée et industrialisée permet de supporter de nombreux cas d'usage, différents modèles et des déploiements à grande échelle, avec optimisation continue. | D10: L'entreprise gouverne sa plateforme IA en tant qu'asset industriel et supporte de nombreux cas d'usage avec différents modèles à grande échelle. | E10: L'omission des enjeux de l'évolution continue des données d'entrée et des cas d'usage ne permettent pas de lever les blocages structurels liés aux performances de l'IA. | F10: Acquérir la capacité d'une plateforme IA gouvernée et évolutive permettant de supporter de nombreux cas d’usage et déploiements à grande échelle. | G10: Étendre la plateforme aux différents domaines ; standardiser les services communs ; automatiser le passage à l’échelle et l’optimisation continue. | H10: Une plateforme IA gouvernée supporte de nombreux cas d’usage et déploiements à grande échelle.

Sheet Q02
A1: {=INDIRECT("IndexQuestions!A" & (A2+3)) & " - " & INDIRECT("IndexQuestions!B" & (A2+3)) & " - " & INDIRECT("IndexQuestions!C" & (A2+3)) & " - " & INDIRECT("IndexQuestions!D" & (A2+3))} -> Q02 - POTENTIEL - Structuration - Data
A2: {=RIGHT(CELL("nomfichier",A3),2)} -> 02 | B2: {=INDIRECT("IndexQuestions!E" & (A2+3))} -> Dans quelle mesure l’entreprise dispose-t-elle de données accessibles, fiables et exploitables pour ses usages d’IA ?
A3: Logique | B3: ='Q01'!B3 -> À chaque score : acquis → blocage vers le niveau suivant → capacité à acquérir → actions prioritaires → résultat attendu.
A4: Score | B4: Thème | C4: Réponse | D4: Ce qui est déjà acquis | E4: Ce qui bloque l’étape suivante | F4: Capacités à acquérir | G4: Actions prioritaires | H4: Résultats attendus
A5: 0 | B5: Absente | C5: Aucune donnée pertinente identifiée. | D5: Aucune donnée pertinente identifiée. | E5: L'entreprise n'a pas identifié les 1ères données à exploiter même si elles sont dispersées. | F5: Acquérir la capacité à identifier (inventaire) et rendre disponibles les données pertinentes pour les usages d’IA. | G5: Identifier des sources pertinentes, leurs propriétaires et les règles d’accès ; définir les premières règles de qualité. | H5: Les données pertinentes pour les premiers usages IA sont identifiées et accessibles.
A6: 1 | B6: Fragmentée | C6: Données dispersées, difficilement accessibles et de qualité incertaine. | D6: L'entreprise possède des données de qualités incertaines présentes et dispersées. | E6: L'entreprise n'a pas proposé de données pertinentes pour une exploitation IA. | F6: Acquérir la capacité à rendre les données pertinentes accessibles et à améliorer leur qualité. | G6: Cartographier les données dispersées ; traiter les principales incohérences ; définir des règles communes de qualité et de documentation. | H6: Les principales données nécessaires sont identifiées, documentées et progressivement accessibles.
A7: 2 | B7: Disponible | C7: Données pertinentes disponibles pour certains usages, mais encore hétérogènes ou difficiles à exploiter. | D7: L'entreprise a identifié des données pertinentes mais elles sont hétérogènes et disponibles que pour certains usages et difficile à exploiter | E7: L'entreprise a trop de donnés hétérogènes et leur préparation à une exploitation IA est insuffisante. | F7: Acquérir la capacité à préparer, structurer et fiabiliser (standard) les données nécessaires aux différents usages d’IA. | G7: Structurer les données prioritaires ; traiter les problèmes de qualité ; préparer les données aux usages IA ciblés. | H7: Les données prioritaires sont suffisamment structurées et fiables pour plusieurs usages.
A8: 3 | B8: Exploitable | C8: Données accessibles, structurées ou préparées et suffisamment fiables pour développer des solutions IA. | D8: L'entreprise offre des données fiables et accessibles pour développer des solutions IA à ses collaborateurs. | E8: La présence de données fiables et accessibles ne suffit pas à mettre en place une gouvernance data dédiée IA. | F8: Acquérir la capacité à fournir des données suffisamment structurées, accessibles et fiables, de manière automatisé, pour développer des solutions IA de manière reproductible. | G8: Industrialiser préparation et mise à disposition ; mettre en place contrôles qualité, processus reproductibles et documentation. | H8: Les équipes disposent de données accessibles, structurées et fiables pour développer des solutions IA de façon reproductible.
A9: 4 | B9: Industrialisée | C9: Données gouvernées, cataloguées, contrôlées et alimentées par des pipelines permettant des usages IA reproductibles. | D9: L'entreprise a un processus de gouvernance de données dans un environnement industrialisé, permettant un usage IA reproductible. | E9: La mutualisation des processus data ne suffit pas à passer à l'échelle pour renforcer une usage des applications IA de qualité. | F9: Acquérir la capacité à gouverner, cataloguer, contrôler et alimenter les données nécessaires aux usages IA au moyen de plateformes automatisées et reproductibles. | G9: Mettre en place catalogage, gouvernance et contrôles systématiques des sources de données ; industrialiser les pipelines et assurer la traçabilité. | H9: Les sources de données IA sont gouvernées, cataloguées et alimentées par des pipelines reproductibles.
A10: 5 | B10: Data-ready | C10: Environnement data industrialisé permettant d'alimenter, à grande échelle, différents usages IA avec qualité, traçabilité, automatisation et réutilisabilité. | D10: Environnement data de l'entreprise est exploité à grande échelle rendant possible l'automatisation et la réutilisation de qualité. | E10: Même si les données sont gouvernées une adaptation continue aux technologies de l'IA nécessite de raffiner les usages pour en tirer le maximum de valeur pour l'entreprise. | F10: Acquérir la capacité à s'adapter à une gouvernance de la donnée évolutive tout en alimentant à grande échelle différents usages IA avec des données produits et/ou services de qualité, traçables, automatisées et réutilisables. | G10: Inculre une analyse de risque dans la gouvernance des donéens. Étendre l’environnement data ; automatiser alimentation et contrôles ; renforcer qualité, traçabilité et réutilisabilité à grande échelle. | H10: Un pilotage de la gouvernance data par les risques. Un environnement data-ready alimente différents usages IA à grande échelle.

Sheet Q03
A1: {=INDIRECT("IndexQuestions!A" & (A2+3)) & " - " & INDIRECT("IndexQuestions!B" & (A2+3)) & " - " & INDIRECT("IndexQuestions!C" & (A2+3)) & " - " & INDIRECT("IndexQuestions!D" & (A2+3))} -> Q03 - POTENTIEL - Industrialisation - Cas d'usage potentiels
A2: {=RIGHT(CELL("nomfichier",A3),2)} -> 03 | B2: {=INDIRECT("IndexQuestions!E" & (A2+3))} -> Dans quelle mesure les activités de l’entreprise présentent-elles un potentiel d’application de l’IA ?
A3: Logique | B3: ='Q01'!B3 -> À chaque score : acquis → blocage vers le niveau suivant → capacité à acquérir → actions prioritaires → résultat attendu.
A4: Score | B4: Thème | C4: Réponse | D4: Ce qui est déjà acquis | E4: Ce qui bloque l’étape suivante | F4: Capacités à acquérir | G4: Actions prioritaires | H4: Résultats attendus
A5: 0 | B5: Aucun potentiel identifié | C5: Aucun cas d'usage IA pertinent identifié. | D5: Aucun cas d'usage pertinent. | E5: Absence d'identification de cas d'usage IA | F5: Acquérir la capacité à identifier les opportunités dans lesquelles l’IA pourrait présenter un cas d’usage pertinent. | G5: Identifier les activités et processus susceptibles de bénéficier de l’IA ; recueillir les besoins métiers et documenter les opportunités. | H5: Un premier ensemble de cas d’usage IA pertinents est identifié.
A6: 1 | B6: Potentiel limité | C6: Quelques opportunités ponctuelles, avec un impact potentiel limité. | D6: L'entreprise a identifié quelques opportunités ponctuelles avec des impacts limités.. | E6: Le nombre de cas d'usage est insuffisant et limite la vision du potentiel et de la valeur de l'IA. | F6: Acquérir la capacité d'augmenter le nombre d'opportunités d’application de l’IA au-delà des expérimentations ponctuelles. | G6: Élargir l’analyse à plusieurs activités ; qualifier les opportunités selon bénéfices, faisabilité et contraintes. | H6: Plusieurs opportunités IA sont identifiées et leur intérêt est caractérisé.
A7: 2 | B7: Potentiel identifié | C7: Plusieurs cas d'usage pertinents ont été identifiés dans certaines activités. | D7: Plusieurs cas d'usage de l'IA identifiés pour certaines activités. | E7: L'insuffisance du nombre de cas d'usage bloque l'évaluation de la valeur ajoutée de l'IA. | F7: Acquérir la capacité à qualifier les différents cas d’usage IA identifiés dans les activités (processus, produits ou services) de l’entreprise. | G7: Évaluer les cas d’usage selon valeur, faisabilité, données, risques et effort ; sélectionner les opportunités à expérimenter. | H7: Les cas d’usage prioritaires sont qualifiés pour une expérimentation structurée.
A8: 3 | B8: Potentiel significatif | C8: L'IA peut améliorer significativement plusieurs processus, produits ou services. | D8: Identification de cas d'usage pouvant améliorer significativement plusieurs processus, produits ou services. | E8: Absence d'analyse de la transformation par l'AI des activités générant de la valeur pour l'entreprise. | F8: Acquérir la capacité à identifier comment l’IA peut générer de la valeur significativement sur plusieurs processus, produits ou services. | G8: Quantifier les valeurs que l'IA peut transformer ou ajouter pour l'entreprise ; mesurer les gains et capitaliser les cas reproductibles. | H8: L’IA produit des améliorations mesurables sur plusieurs processus, produits ou services.
A9: 4 | B9: Potentiel élevé | C9: L'IA peut transformer plusieurs activités clés ou générer de nouvelles sources importantes de valeur. | D9: Identification de cas d'usage pouvant transformer les activités de l'entreprise en générant de la valeur. | E9: Une analyse complète du portefeuille de projets IA est manquante pour transformer le modèle opérationnel de l'entreprise. | F9: Acquérir la capacité à utiliser l’IA pour transformer plusieurs activités clés ou générer de nouvelles sources importantes de valeur. | G9: Identifier les activités clés transformables significateivement par l'IA ; concevoir des cas d’usage à fort impact et intégrer l’IA aux évolutions métier. | H9: Plusieurs activités clés exploitent l’IA pour améliorer leurs performances ou créer de la valeur.
A10: 5 | B10: Potentiel stratégique | C10: L'IA est susceptible de transformer en profondeur le modèle opérationnel, les produits/services ou les sources de valeur de l'entreprise. | D10: Les modes opérationnels de l'entreprises sont stratégiquement modifiés par l'apport de l'IA et les sources de valeurs sont démontrées. | E10: L'entreprise est mature sur ses potentiels de projet IA générant des actifs mais il doit avoir une attention particulière aux enjeux d'activation et de renouvellement de la valeur, pour l'inscrire dans sa stratégie. | F10: Acquérir la capacité à intégrer l’IA comme levier de transformation du modèle opérationnel, des produits, des services ou des sources de valeur. | G10: Intégrer systématiquement l’IA dans les réflexions sur modèle opérationnel, produits, services et sources de valeur ; réévaluer les opportunités. | H10: L’IA est intégrée aux évolutions stratégiques et opérationnelles comme levier de transformation.

Sheet Q04
A1: {=INDIRECT("IndexQuestions!A" & (A2+3)) & " - " & INDIRECT("IndexQuestions!B" & (A2+3)) & " - " & INDIRECT("IndexQuestions!C" & (A2+3)) & " - " & INDIRECT("IndexQuestions!D" & (A2+3))} -> Q04 - STRATÉGIE - Emergence - Ambition IA
A2: {=RIGHT(CELL("nomfichier",A3),2)} -> 04 | B2: {=INDIRECT("IndexQuestions!E" & (A2+3))} -> Quel est le niveau d’ambition de l’entreprise concernant l’IA ?
A3: Logique | B3: ='Q01'!B3 -> À chaque score : acquis → blocage vers le niveau suivant → capacité à acquérir → actions prioritaires → résultat attendu.
A4: Score | B4: Thème | C4: Réponse | D4: Ce qui est déjà acquis | E4: Ce qui bloque l’étape suivante | F4: Capacités à acquérir | G4: Actions prioritaires | H4: Résultats attendus
A5: 0 | B5: Absente | C5: L’IA ne fait pas partie des réflexions ou ambitions de l’entreprise. | D5: Aucune ambition. | E5: L'IA absente des réflexions stratégiques de l'entreprise. | F5: Acquérir la capacité à intégrer l’IA dans les réflexions et ambitions de l’entreprise auprès des managers. | G5: Sensibiliser les dirigeants aux possibilités et enjeux de l’IA ; organiser une première réflexion sur les ambitions possibles. | H5: L’IA est intégrée aux réflexions de l’entreprise et une première ambition est exprimée.
A6: 1 | B6: Exploratoire | C6: L’entreprise commence à explorer les possibilités offertes par l’IA. | D6: Les exploration des possibilités de l'IA sont en cours dans l'entreprise. | E6: Une ambition d'entreprise non traduite en choix de quelques initiatives ciblées. | F6: Acquérir la capacité à définir une vision des possibilités offertes par l’IA. | G6: Structurer l’exploration des opportunités ; sélectionner des domaines d’intérêt et documenter les enseignements. | H6: L’entreprise dispose d’une compréhension initiale des opportunités IA et de domaines d’exploration identifiés.
A7: 2 | B7: Expérimentation | C7: L’entreprise affiche une volonté de développer l’IA à travers quelques initiatives ciblées. | D7: L'entreprise montre une volonté de développement IA sur quelques initiatives ciblées. | E7: L'entreprise manque d'objectifs pour des choix de projets IA | F7: Acquérir la capacité à transformer la vision IA de l'entreprise en initiatives ciblées et cohérentes avec les activités de l’entreprise. | G7: Transformer les expérimentations en initiatives ciblées ; préciser les objectifs et relier les initiatives aux besoins des activités. | H7: Les initiatives IA répondent à des objectifs identifiés et forment une ambition cohérente.
A8: 3 | B8: Ambition définie | C8: Des objectifs explicites concernant l’IA sont définis au niveau de l’entreprise ou de plusieurs activités. | D8: L'entreprise a défini des objectifs explicites pour des usages de l'IA. | E8: Dans sa stratégie, l'entreprise manque de levier IA pour transformer ses activités. | F8: Acquérir la capacité à définir des objectifs explicites concernant l’IA au niveau de l’entreprise ou de plusieurs activités. | G8: Formaliser les objectifs IA ; les décliner par activités et définir les indicateurs de suivi. | H8: Des objectifs IA explicites sont partagés et servent de référence aux initiatives.
A9: 4 | B9: Transformation | C9: L’IA constitue un levier identifié de transformation des activités, produits, services ou opérations. | D9: L'entreprise a identifié que l'IA est un levier de transformation de son activités, de ses produits ou services. | E9: L'entreprise manque d'orchestration transverse pour affiner son ambition stratégique de considérer l'IA comme levier majeur de sa transformation | F9: Acquérir la capacité à utiliser l’IA comme levier stratégique identifié de transformation des activités, produits, services ou opérations. | G9: Intégrer l’IA aux transformations des activités, produits, services ou opérations ; aligner investissements et priorités. | H9: L’IA est mobilisée comme levier de transformation et intégrée aux priorités.
A10: 5 | B10: Ambition stratégique | C10: L’IA est considérée comme un levier majeur d’évolution du positionnement et/ou du modèle économique de l’entreprise. | D10: L'entreprise place l'IA comme levier stratégique de son positionnement et/ou modèle économique. | E10: L'entreprise est mature sur l'émergence d'une stratégie IA mais il doit avoir une attention particulière aux enjeux d'anticipation et de renouvellement de cette dernière. | F10: Acquérir la capacité à intégrer l’IA comme levier majeur d’évolution du positionnement ou du modèle économique de l’entreprise (Stratégie AI-Native). | G10: Inscrire l’IA dans l’évolution du positionnement et/ou du modèle économique ; réévaluer régulièrement l’ambition. | H10: L’IA est intégrée aux choix stratégiques et son ambition évolue avec le contexte.

Sheet Q05
A1: {=INDIRECT("IndexQuestions!A" & (A2+3)) & " - " & INDIRECT("IndexQuestions!B" & (A2+3)) & " - " & INDIRECT("IndexQuestions!C" & (A2+3)) & " - " & INDIRECT("IndexQuestions!D" & (A2+3))} -> Q05 - STRATÉGIE - Structuration - Feuille de route
A2: {=RIGHT(CELL("nomfichier",A3),2)} -> 05 | B2: {=INDIRECT("IndexQuestions!E" & (A2+3))} -> Dans quelle mesure l’entreprise dispose-t-elle d’une feuille de route pour mettre en œuvre son ambition IA ?
A3: Logique | B3: ='Q01'!B3 -> À chaque score : acquis → blocage vers le niveau suivant → capacité à acquérir → actions prioritaires → résultat attendu.
A4: Score | B4: Thème | C4: Réponse | D4: Ce qui est déjà acquis | E4: Ce qui bloque l’étape suivante | F4: Capacités à acquérir | G4: Actions prioritaires | H4: Résultats attendus
A5: 0 | B5: Aucune feuille de route | C5: Aucune action ou trajectoire IA définie. | D5: Aucune trajectoire. | E5: Absence d'actions coordonnées pour structurer la feuille de route IA. | F5: Acquérir la capacité à définir une première trajectoire d’actions permettant de mettre en œuvre l’ambition IA. | G5: Recenser initiatives et besoins IA ; définir premières étapes, responsables et échéances ; formaliser une trajectoire initiale. | H5: Une première trajectoire IA existe avec actions et responsabilités identifiées.
A6: 1 | B6: Initiatives ponctuelles | C6: Quelques initiatives existent sans trajectoire commune. | D6: Des initiatives ponctuelles existent au sein de l'entreprise sans avoir pour autant une trajectoire commune. | E6: Manque d'une trajectoire commune au sein de l'entreprise pour les nouveaux projets IA. | F6: Acquérir la capacité à coordonner les initiatives IA existantes autour d’une trajectoire commune. | G6: Regrouper les initiatives ; identifier dépendances et priorités ; construire une trajectoire commune. | H6: Les principales initiatives IA sont coordonnées dans une trajectoire commune.
A7: 2 | B7: Roadmap émergente | C7: Des initiatives sont regroupées et une première trajectoire est en cours de définition. | D7: Les initiatives de l'entreprise sont regroupées dans une roadmap émergente et une première trajectoire est en cours de définition. | E7: Insuffisance des définitions des objectifs, des échéances et des dépendances au sein la roadmap IA de l'entreprise. | F7: Acquérir la capacité à structurer les initiatives IA dans une première feuille de route cohérente. | G7: Structurer les initiatives en chantiers ; définir objectifs, échéances, responsables et dépendances ; consolider la roadmap. | H7: Une roadmap IA cohérente permet de suivre les principales initiatives.
A8: 3 | B8: Roadmap structurée | C8: Une feuille de route IA définit des initiatives, des échéances et des objectifs. | D8: L'entreprise a une feuille de route IA structurée qui définit les initiatives, les échéances et les objectifs. | E8: Lacunes dans le pilotage et l'intégration de la feuille de route au plan stratégique de l'entreprise. | F8: Acquérir la capacité à intégrer et piloter la feuille de route IA dans les plans de l’entreprise au moyen d’indicateurs. | G8: Intégrer la roadmap aux plans de l’entreprise ; définir indicateurs, revues et arbitrages. | H8: La roadmap IA est pilotée avec objectifs, échéances et indicateurs intégrés au pilotage.
A9: 4 | B9: Roadmap pilotée | C9: La feuille de route est intégrée aux plans de l’entreprise et régulièrement pilotée avec des indicateurs. | D9: La feuille de route IA est intégrée aux plans de l’entreprise et régulièrement pilotée avec des indicateurs. | E9: Absence d'une trajectoire pluriannuelle pour optimiser et adapter transversalement le pilotage de la roadmap IA | F9: Acquérir la capacité à orchestrer une trajectoire pluriannuelle IA en adaptant les initiatives, leur passage à l’échelle en fonction des résultats des projets IA et des prioités entreprises. | G9: Construire une trajectoire pluriannuelle transversale ; coordonner investissements et passage à l’échelle au niveau de la direction de l'entreprise; adapter la roadmap aux résultats. | H9: La transformation IA est pilotée au niveau de la direction de l'entreprise dans la durée avec des arbitrages fondés sur résultats et priorités.
A10: 5 | B10: Transformation orchestrée | C10: Une trajectoire pluriannuelle coordonne les initiatives IA, leur passage à l’échelle et leur évolution en fonction des résultats et des priorités de l’entreprise. | D10: L'entreprise a une trajectoire pluriannuelle et orchestrée qui coordonne les initiatives IA, leur passage à l’échelle et leur évolution en fonction des résultats et des priorités de l’entreprise. | E10: L'entreprise est mature sur la structuration de sa stratégie IA intégré au plan de l'entreprise mais il doit avoir une attention particulière aux enjeux d'activation et d'adaptation permanente. | F10: Acquérir la capacité d'adapter sa trajectoire pluriannuelle IA en ajustant la roadmap IA à l'évolution de l'écosysteme technologique et du contexte économique de l'entreprise. | G10: Mettre en place une veille technologique pro-active ; mettre en place une gouvernance dynamique à l'écoute de l'ecosystème économique de l'entreprise ; réallouer régulièrement les ressources et intégrer nouveaux usages et opportunités. | H10: La trajectoire IA évolue continuellement selon la valeur créée, les priorités, le contexte technologique et économique.

Sheet Q06
A1: {=INDIRECT("IndexQuestions!A" & (A2+3)) & " - " & INDIRECT("IndexQuestions!B" & (A2+3)) & " - " & INDIRECT("IndexQuestions!C" & (A2+3)) & " - " & INDIRECT("IndexQuestions!D" & (A2+3))} -> Q06 - STRATÉGIE - Industrialisation - Portefeuille/priorisation
A2: {=RIGHT(CELL("nomfichier",A3),2)} -> 06 | B2: {=INDIRECT("IndexQuestions!E" & (A2+3))} -> Dans quelle mesure les initiatives et cas d’usage IA sont-ils priorisés en fonction des enjeux de l’entreprise ?
A3: Logique | B3: ='Q01'!B3 -> À chaque score : acquis → blocage vers le niveau suivant → capacité à acquérir → actions prioritaires → résultat attendu.
A4: Score | B4: Thème | C4: Réponse | D4: Ce qui est déjà acquis | E4: Ce qui bloque l’étape suivante | F4: Capacités à acquérir | G4: Actions prioritaires | H4: Résultats attendus
A5: 0 | B5: Aucun cas d’usage | C5: Aucun cas d’usage IA identifié. | D5: Aucun cas d'usage. | E5: L'entreprise n'a pas identifié de cas d'usage permettant un début de gestion de portefeuille projet IA. | F5: Acquérir la capacité à identifier des cas d’usage IA répondant aux enjeux de l’entreprise. | G5: Recenser les premiers cas d’usage IA en lien avec les enjeux métiers ; documenter opportunités et besoins. | H5: Un portefeuille initial de cas d’usage IA est identifié.
A6: 1 | B6: Exploration | C6: Quelques cas d’usage sont identifiés sans véritable priorisation. | D6: L'entreprise présente quelques cas d’usage identifiés sans véritable priorisation. | E6: Manque de cas d'usage IA permettant de débuter des analyses de priorisation par l'entreprise. | F6: Acquérir la capacité à recenser les cas d’usage IA et à commencer à les comparer. | G6: Complèter les cas d'usage IA de l'entreprise ; définir des critères de comparaison ; analyser les cas selon intérêt, faisabilité et effort. | H6: Les cas d’usage commencent à être comparés sur une base commune.
A7: 2 | B7: Identification | C7: Plusieurs cas d’usage sont recensés et font l’objet d’une première analyse. | D7: L'entreprise a recensé plusieurs cas d’usage qui font l’objet d’une première analyse. | E7: Analyse incomplète suivant la valeur, la faisabilité, les risques et l'effort permettant un arbitrage formalisé. | F7: Acquérir la capacité à analyser et prioriser les cas d’usage IA selon leur valeur, leur faisabilité, leurs risques et leurs principaux enjeux. | G7: Formaliser l’analyse de valeur, faisabilité, risques et effort ; préparer une première sélection. | H7: Les cas d’usage sont suffisamment qualifiés pour être priorisés.
A8: 3 | B8: Priorisation | C8: Les cas d’usage sont priorisés selon des critères explicites tels que valeur, faisabilité, risques ou effort. | D8: L'entreprise a priorisé les cas d’usage identifiés selon des critères explicites tels que valeur, faisabilité, risques ou effort. | E8: L'entreprise ne fait pas de gestion des projets IA, pourtant priorisés, au sein d'un portefeuille projet permettant de faire l'allocation et le suivit de l'investissements IA. | F8: Acquérir la capacité à gérer au sein d'un portefeuille les cas d’usage IA pour contrôller leur progression et leur cout. | G8: Collecter l'ensemble des cas dusage IA au sein d'un portefeuille ; Mettre en place un processus de priorisation sur les critères de valeur apportée, faisabilité, risques et efforts ; arbitrer les investissements et suivre les cas sélectionnés. | H8: Un portefeuile est disponible auprès des parties prenantes des projets IA ; les initiatives IA sont priorisées et suivies selon des critères explicites.
A9: 4 | B9: Portefeuille piloté | C9: Les initiatives sont gérées comme un portefeuille, avec arbitrage des investissements et suivi de leur progression. | D9: L'entreprise gère ses initiatives IA dans un portefeuille avec un arbitrage des investissements et un suivi de leur progression. | E9: Manque de réévaluation continue du portefeuille des projets IA permettant d'identifier les nouvelles opportunités de l'entreprise. | F9: Acquérir la capacité à réévaluer continuellement le portefeuille IA en fonction de la valeur créée, des résultats, des nouvelles opportunités et des priorités de l’entreprise. | G9: Mettre en place des routines de reveu du portefeuille de proejt IA ; gérer les nouvelles initiatives dans le portefeuille ; arbitrer les investissements et suivre valeur, coûts, risques et progression. | H9: Les investissements IA sont pilotés au sein d'un portefeuille cohérent avec des indicateurs clefs de processus (KPI).
A10: 5 | B10: Optimisation continue | C10: Le portefeuille est régulièrement réévalué en fonction de la valeur créée, des résultats obtenus, des nouvelles opportunités et de l’évolution des priorités de l’entreprise. | D10: Le portefeuille des projets IA de l'entreprise est régulièrement réévalué en fonction de la valeur créée, des résultats obtenus, des nouvelles opportunités et de l’évolution des priorités de l’entreprise. | E10: L'entreprise est mature sur la gestion de son portefeuille de projets IA mais il doit avoir une attention particulière aux enjeux d'activation et d'adaptation permanente. | F10: Acquérir la capacité d'adapter le contenu de son portefeuille projets en ajustant les décisions en fonction de l'évolution de l'écosysteme technologique et du contexte économique de l'entreprise. | G10: Mettre en place une veille technologique pro-active ; mettre en place une gouvernance dynamique à l'écoute de l'ecosystème économique de l'entreprise ; réévaluer périodiquement le portefeuille selon valeur, résultats, opportunités et priorités ; réallouer les ressources. | H10: Le portefeuille IA évolue continuellement pour concentrer les ressources sur les opportunités pertinentes et les adapter suivant le contexte technologique et économique.

Sheet Q07
A1: {=INDIRECT("IndexQuestions!A" & (A2+3)) & " - " & INDIRECT("IndexQuestions!B" & (A2+3)) & " - " & INDIRECT("IndexQuestions!C" & (A2+3)) & " - " & INDIRECT("IndexQuestions!D" & (A2+3))} -> Q07 - CULTURE - Emergence - Leadership
A2: {=RIGHT(CELL("nomfichier",A3),2)} -> 07 | B2: {=INDIRECT("IndexQuestions!E" & (A2+3))} -> Dans quelle mesure les dirigeants et managers favorisent-ils l’adoption de l’IA dans l’entreprise ?
A3: Logique | B3: ='Q01'!B3 -> À chaque score : acquis → blocage vers le niveau suivant → capacité à acquérir → actions prioritaires → résultat attendu.
A4: Score | B4: Thème | C4: Réponse | D4: Ce qui est déjà acquis | E4: Ce qui bloque l’étape suivante | F4: Capacités à acquérir | G4: Actions prioritaires | H4: Résultats attendus
A5: 0 | B5: Absence d'implication | C5: Les dirigeants et managers ne manifestent pas d'intérêt ou d'implication vis-à-vis de l'IA. | D5: Absence d'implication | E5: Les managers ne sont pas sensibilisés à l'IA | F5: Acquérir la capacité du leadership à comprendre les enjeux de l’IA et à identifier les premières opportunités d’utilisation dans l’entreprise. | G5: Sensibiliser dirigeants et managers aux enjeux IA ; identifier les premiers sponsors et clarifier leur rôle. | H5: Les premiers sponsors comprennent les enjeux IA et commencent à soutenir le sujet.
A6: 1 | B6: Sensibilisation | C6: Le sujet est connu des dirigeants et managers, mais sans implication concrète. | D6: Le leadership de l'entreprise est sensibilisé aux sujets IA | E6: la hiérarchie de l'entreprise ne soutien pas les initiatives IA de ses collaborateurs. | F6: Acquérir la capacité du leadership à soutenir et à rendre visibles les premières initiatives IA portées par les collaborateurs. | G6: Nommer des sponsors ; communiquer les objectifs IA ; donner de la visibilité aux initiatives des collaborateurs. | H6: Le leadership IA devient visible et les initiatives bénéficient d’un soutien identifié.
A7: 2 | B7: Soutien ponctuel | C7: Certains dirigeants ou managers soutiennent des initiatives IA, principalement au niveau de projets individuels. | D7: La hiérarchie de l'entreprise soutient des initiatives IA ponctuellement | E7: Le leadership de l'entreprise n'encourage pas l'utilisation de l'IA au quotidien. | F7: Acquérir la capacité des managers à encourager et accompagner l’utilisation de l’IA dans les activités quotidiennes de leurs équipes. | G7: Former les managers ; partager des cas concrets ; leur donner les moyens d’encourager et d’accompagner les expérimentations. | H7: Les managers soutiennent plus régulièrement les initiatives et encouragent les usages.
A8: 3 | B8: Soutien managérial | C8: Les managers encouragent l'expérimentation et l'utilisation de l'IA dans leurs équipes. | D8: L'entreprise encourage l'expérimentation et l'utilisation de l'IA dans les équipes | E8: Le leadership de l'entreprise n'est pas actif dans l'adoption de l'IA au quotidien. | F8: Acquérir la capacité du management à faire de l’utilisation de l’IA une pratique encouragée et intégrée dans le fonctionnement des équipes. | G8: Mettre en place des rituels managériaux ; valoriser les comportements attendus ; aligner les pratiques sur les objectifs d’adoption. | H8: L’utilisation et l’expérimentation de l’IA sont durablement encouragées dans les équipes.
A9: 4 | B9: Leadership actif | C9: Les dirigeants et managers portent activement l'adoption de l'IA et accompagnent sa diffusion dans l'entreprise. | D9: L'entreprise est active dans l'adoption de l'IA par les collaborateurs et accompagne sa diffusion dans l'entreprise | E9: Le leadership de l'entreprise n'incarne pas assez l'adoption de l'IA au quotidien, cela n'est pas assez visible auprès de ses collaborateurs | F9: Acquérir la capacité des dirigeants et managers à incarner activement l’utilisation de l’IA et à en accompagner la diffusion dans l’ensemble de l’entreprise. | G9: Faire utiliser et promouvoir l’IA par dirigeants et managers ; intégrer les usages dans les pratiques managériales ; rendre l’exemplarité visible. | H9: Le leadership incarne activement l’adoption de l’IA et fournit un modèle visible aux collaborateurs.
A10: 5 | B10: Leadership exemplaire | C10: Le leadership IA est visible dans les pratiques managériales et les dirigeants incarnent eux-mêmes l'utilisation et l'adoption de l'IA. | D10: La culture de l'AI est exemplaire dans l'entreprise qui incarne une adoption et une utilisation de l'IA au sein des équipes | E10: La culture de l'IA est acquise au sein de l'entreprise mais il manque une gouvernance durable de la prévoyance et du maintien des compétences. | F10: Acquérir la capacité du leadership à maintenir durablement une culture d’adoption de l’IA en faisant évoluer les pratiques managériales et l’exemplarité des dirigeants. | G10: Capitaliser sur les pratiques de leadership ; partager les retours ; renouveler les pratiques et maintenir l’exemplarité dans la durée. | H10: L’adoption de l’IA est portée durablement par un leadership exemplaire et évolutif.

Sheet Q08
A1: {=INDIRECT("IndexQuestions!A" & (A2+3)) & " - " & INDIRECT("IndexQuestions!B" & (A2+3)) & " - " & INDIRECT("IndexQuestions!C" & (A2+3)) & " - " & INDIRECT("IndexQuestions!D" & (A2+3))} -> Q08 - CULTURE - Structuration - Appropriation
A2: {=RIGHT(CELL("nomfichier",A3),2)} -> 08 | B2: {=INDIRECT("IndexQuestions!E" & (A2+3))} -> Dans quelle mesure les collaborateurs sont-ils prêts à adopter et utiliser l’IA dans leur activité ?
A3: Logique | B3: ='Q01'!B3 -> À chaque score : acquis → blocage vers le niveau suivant → capacité à acquérir → actions prioritaires → résultat attendu.
A4: Score | B4: Thème | C4: Réponse | D4: Ce qui est déjà acquis | E4: Ce qui bloque l’étape suivante | F4: Capacités à acquérir | G4: Actions prioritaires | H4: Résultats attendus
A5: 0 | B5: Résistance | C5: L'IA suscite principalement de la crainte, de la méfiance ou une résistance à son utilisation. | D5: Pas d'implication réelle. | E5: Manque de confiance et de légitimité managériale provoquant une forte résistance sur la mise en place de l'IA au sein de l'entreprise. | F5: Acquérir la capacité à créer les conditions permettant aux collaborateurs d’accepter progressivement l’utilisation de l’IA. | G5: Expliquer enjeux et bénéfices ; partager la vision entreprise sur l'IA. | H5: Les résistances sont identifiées et les collaborateurs disposent de premiers repères pour envisager l’IA.
A6: 1 | B6: Distance | C6: Les collaborateurs connaissent le sujet mais restent largement indifférents ou peu concernés. | D6: Les collaborateurs de l'entreprise connaissent le sujet mais restent largement indifférents ou peu concernés. | E6: L'entreprise n'est pas curieuse sur les initiatives de ses collaborateurs par le manque de relais actifs sur l'IA. | F6: Acquérir la capacité à susciter l’intérêt des collaborateurs et leur implication dans les usages de l’IA. | G6: Proposer des ateliers pouvant fare naitre des usages simples et sécurisés pour une première expérience ; identifier les collaborateurs intéressés. | H6: Les collaborateurs perçoivent mieux l’intérêt concret de l’IA et certains expérimentent.
A7: 2 | B7: Curiosité | C7: Une partie des collaborateurs manifeste de l'intérêt et commence à expérimenter l'IA. | D7: Une partie des collaborateurs de l'entreprise manifeste de l'intérêt et commence à expérimenter l'IA. | E7: L'entreprise ne s'engage pas de manière homogène sur les initiative de projets IA de ses collaborateurs. | F7: Acquérir la capacité à transformer la curiosité et les premières expérimentations en usages concrets de l’IA. | G7: Accompagner les expérimentations ; faciliter l’accès aux outils autorisés ; partager les retours et diffuser les usages utiles; présenter des cas d’usage liés aux activités ; organiser démonstrations et expérimentations. | H7: Les expérimentations se transforment progressivement en usages concrets.
A8: 3 | B8: Acceptation | C8: L'utilisation de l'IA est globalement acceptée et commence à entrer dans les pratiques de travail. | D8: Les managers encouragent l'utilisation de l'IA au sein e l'entreprise qui est globalement acceptée et commence à entrer dans les pratiques de travail. | E8: L'entreprise ne s'est pas approprié l'ensemble des initiative de projets IA de ses collaborateurs permettant de renforcer son leadership transverse. | F8: Acquérir la capacité à favoriser l’utilisation spontanée de l’IA et le partage des expériences entre collaborateurs. | G8: Identifier les usages pertinents ; formaliser les bonnes pratiques ; accompagner les équipes dans l’intégration de l’IA au quotidien. | H8: L’utilisation de l’IA devient une pratique acceptée et régulière dans une part croissante des activités.
A9: 4 | B9: Appropriation | C9: Les collaborateurs utilisent spontanément l'IA pour améliorer leurs activités et partagent leurs expériences. | D9: Les collaborateurs de l'entreprise utilisent spontanément l'IA pour améliorer leurs activités et partagent leurs expériences soutenu par un leadership actif. | E9: L'entreprise ne favorise pas assez l'usage de l'IA pour transformer ses pratiques professionnelles. | F9: Acquérir la capacité à faire évoluer continuellement les pratiques professionnelles grâce à l’intégration de l’IA. | G9: Structurer les communautés de pratique ; diffuser les usages reproductibles ; intégrer les retours dans l’évolution des processus. | H9: Les collaborateurs s’approprient l’IA, partagent leurs pratiques et contribuent à sa diffusion.
A10: 5 | B10: Transformation des pratiques | C10: Les collaborateurs contribuent activement à faire évoluer les usages de l'IA et intègrent celle-ci dans leurs pratiques professionnelles. | D10: Les collaborateurs contribuent activement à faire évoluer les usages de l'IA et intègrent celle-ci dans leurs pratiques professionnelles soutenu par un leadership exemplaire. | E10: Les collaborateurs de l'entreprise sont encouragés à s'approprier l'IA dans le pratiques quotidiennes mais il peut y avoir un manque d'entretien de la dynamique enclenchée. | F10: Acquérir la capacité à intégrer durablement l’utilisation de l’IA dans les pratiques de travail. | G10: Maintenir expérimentation et partage ; capitaliser les retours ; faire évoluer les pratiques avec les nouveaux usages et apprentissages. | H10: L’IA est durablement intégrée aux pratiques professionnelles et les collaborateurs contribuent à leur évolution.

Sheet Q09
A1: {=INDIRECT("IndexQuestions!A" & (A2+3)) & " - " & INDIRECT("IndexQuestions!B" & (A2+3)) & " - " & INDIRECT("IndexQuestions!C" & (A2+3)) & " - " & INDIRECT("IndexQuestions!D" & (A2+3))} -> Q09 - CULTURE - Industrialisation - Apprentissage & collaboration
A2: {=RIGHT(CELL("nomfichier",A3),2)} -> 09 | B2: {=INDIRECT("IndexQuestions!E" & (A2+3))} -> Dans quelle mesure l’entreprise favorise-t-elle l’apprentissage, l’expérimentation et le partage autour de l’IA ?
A3: Logique | B3: ='Q01'!B3 -> À chaque score : acquis → blocage vers le niveau suivant → capacité à acquérir → actions prioritaires → résultat attendu.
A4: Score | B4: Thème | C4: Réponse | D4: Ce qui est déjà acquis | E4: Ce qui bloque l’étape suivante | F4: Capacités à acquérir | G4: Actions prioritaires | H4: Résultats attendus
A5: 0 | B5: Aucun dispositif | C5: Aucun dispositif d'apprentissage, d'expérimentation ou de partage autour de l'IA. | D5: Il n'y a aucun dispositif d'apprentissage au sein de l'entreprise, d'expérimentation ou de partage autour de l'IA. | E5: Il n'y a pas de dispositifs d'apprentissage informels de l'IA en entreprise. | F5: Acquérir la capacité à mettre en place un premier dispositif d’apprentissage et d’expérimentation. | G5: Identifier les besoins d’apprentissage et d’expérimentation ; mettre en place un premier dispositif de sensibilisation et de partage. | H5: Un premier dispositif permet de découvrir, expérimenter et échanger autour de l’IA.
A6: 1 | B6: Initiatives informelles | C6: Des échanges ou expérimentations existent de manière informelle entre quelques collaborateurs. | D6: L'entreprise note des échanges ou expérimentations de manière informelle entre quelques collaborateurs. | E6: L'entreprise ne soutient pas des initiatives ponctuelles d'ateliers ou de formations auprès de ses collaborateurs | F6: Acquérir la capacité à favoriser les échanges et expérimentations, au sein de communautés IA au-delà des initiatives individuelles. | G6: Structurer les échanges formels au sein de communauté ; identifier les initiatives ; organiser des premiers ateliers et espaces de partage réguliers. | H6: Les initiatives commencent à être coordonnées et accessibles à un public plus large. Une comunauté IA existe au sein de l'entreprise.
A7: 2 | B7: Initiatives ponctuelles | C7: Des ateliers, formations, communautés ou expérimentations sont organisés ponctuellement. | D7: L'entreprise favorise des ateliers, formations, communautés ou expérimentations sont organisés ponctuellement. | E7: L'entreprise ne met pas en place des initiatives régulières de formations et de capitalisation sur l'IA. | F7: Acquérir la capacité à organiser périodiquement la gestion des connaissances au sein d'ateliers, formations, communautés ou expérimentations autour de l’IA. | G7: Planifier ateliers, formations, communautés ou expérimentations ; définir le socle de connaissace nécessaire à l'entreprise ; définir publics et objectifs ; capitaliser les retours. | H7: Des dispositifs réguliers permettent d’apprendre, expérimenter et partager autour de l’IA. Un socle de connaissance IA est débutée.
A8: 3 | B8: Dispositifs réguliers | C8: Des dispositifs réguliers permettent aux collaborateurs d'apprendre, expérimenter et partager autour de l'IA. | D8: L'entreprise met en place des dispositifs réguliers permettant aux collaborateurs d'apprendre, expérimenter et partager autour de l'IA. | E8: Il n'existe pas au sein de l'entreprise de communautés transverses sur l'IA. | F8: Acquérir la capacité à inscrire systèmatiquement l’apprentissage, l’expérimentation et le partage de pratiques IA dans le fonctionnement de l’entreprise. | G8: Ancrer les dispositifs dans le fonctionnement ; organiser leur animation ; mesurer participation et réutilisation des pratiques ; abonder un wiki de connaissance IA de manière autonome par les collaborateurs. | H8: L’apprentissage, l’expérimentation et le partage IA deviennent des pratiques régulières. Le wiki de connaissance IA de l'entreprise est utilisé.
A9: 4 | B9: Communautés actives | C9: Des communautés, réseaux ou espaces de collaboration structurés favorisent la diffusion des pratiques et des retours d'expérience. | D9: L'entreprise favorise des communautés, réseaux ou espaces de collaboration structurés permettant la diffusion des pratiques et des retours d'expérience. | E9: L'entreprise manque d'un apprentissage continu à l'IA intégré dans ses processus de ressource humaine. | F9: Acquérir la capacité à intégrer durablement l’apprentissage, l’expérimentation et le partage de pratiques IA dans le fonctionnement de l’entreprise. | G9: Structurer communautés, réseaux et la gestion des connaissances ; faciliter circulation des pratiques ; relier les communautés aux initiatives IA. | H9: Des communautés actives accélèrent diffusion et capitalisation des expériences. La gestion des connaissances IA de l'entreprise est reconnue par l'ensemble de ses collborateurs.
A10: 5 | B10: Apprentissage continu | C10: L'expérimentation, le partage et l'apprentissage autour de l'IA sont intégrés durablement dans les modes de fonctionnement de l'entreprise. | D10: L'entreprise a mis en place un apprentissage continu ou l'expérimentation, le partage et autour de l'IA sont intégrés durablement dans les modes de fonctionnement de l'entreprise. | E10: Bien que la culture de l'IA est bien implantée dans l'entreprise une attention particulière sur l'adaptabilité aux technologies de l'IA en évolution permanente est nécessaire. | F10: Acquérir la capacité à adapter durablement l’expérimentation, le partage et l’apprentissage IA dans les modes de fonctionnement de l’entreprise. | G10: Intégrer apprentissage et expérimentation dans les processus ; renouveler contenus de la base de connaissance ; capitaliser en continu sur nouveaux usages et résultats. | H10: L’apprentissage, l’expérimentation et le partage IA sont durablement intégrés au fonctionnement. La gestion des connaissances IA de l'entreprise est maintenue à un haut niveau de disponibilité.

Sheet Q10
A1: {=INDIRECT("IndexQuestions!A" & (A2+3)) & " - " & INDIRECT("IndexQuestions!B" & (A2+3)) & " - " & INDIRECT("IndexQuestions!C" & (A2+3)) & " - " & INDIRECT("IndexQuestions!D" & (A2+3))} -> Q10 - COMPÉTENCES - Emergence - Capacité interne
A2: {=RIGHT(CELL("nomfichier",A3),2)} -> 10 | B2: {=INDIRECT("IndexQuestions!E" & (A2+3))} -> Dans quelle mesure l’entreprise dispose-t-elle des compétences internes nécessaires pour concevoir, développer, déployer et exploiter des solutions d’IA ?
A3: Logique | B3: ='Q01'!B3 -> À chaque score : acquis → blocage vers le niveau suivant → capacité à acquérir → actions prioritaires → résultat attendu.
A4: Score | B4: Thème | C4: Réponse | D4: Ce qui est déjà acquis | E4: Ce qui bloque l’étape suivante | F4: Capacités à acquérir | G4: Actions prioritaires | H4: Résultats attendus
A5: 0 | B5: Absentes | C5: L'entreprise ne dispose pas de compétences internes identifiées en IA. | D5: L'entreprise ne dispose pas de compétences internes identifiées en IA. | E5: L'entreprise ne dispose pas de compétences internes identifiées en IA. Elle peut avoir une dépendance totale à l'extérieur. | F5: Acquérir une première capacité interne à concevoir, développer, déployer ou exploiter des solutions d’IA. | G5: Identifier les compétences IA nécessaires ; recenser les compétences existantes et els personnes cibles ; définir les besoins de développement ou recrutement. | H5: Les compétences IA prioritaires et les premiers moyens pour les acquérir sont identifiés.
A6: 1 | B6: Très limitées | C6: Quelques personnes possèdent des connaissances ou compétences IA, sans capacité collective structurée. | D6: L'entreprise a identifiée quelques personnes possédant des connaissances ou compétences IA, sans capacité collective structurée. | E6: L'entreprise dispose trop peu de compétences internes identifiées en IA et n'a pas de capacité collective et possède une couverture insuffisantes des compétences. | F6: Acquérir une capacité collective permettant de réaliser des projets IA au-delà de quelques connaissances individuelles. | G6: Constituer une première équipe ou communauté de compétences ; compléter les connaissances individuelles ; sécuriser les expertises. | H6: Une capacité collective initiale permet de contribuer à des projets IA ciblés.
A7: 2 | B7: Partielles | C7: Une équipe ou plusieurs personnes disposent de compétences permettant de réaliser certains projets IA, mais des compétences importantes manquent. | D7: L'entreprise a définit une équipe ou plusieurs personnes disposant de compétences qui permettent de réaliser certains projets IA, mais des compétences importantes manquent. | E7: L'entreprise ne dispose pas des principales compétences techniques et métier nécessaires pour développer des projets IA. | F7: Acquérir les compétences nécessaires pour couvrir les principales dimensions des projets IA. | G7: Cartographier les compétences manquantes ; compléter les expertises nécessaires aux projets prioritaires : data, IA/ML, ingénierie, intégration ou déploiement. | H7: Les principales compétences nécessaires aux projets prioritaires sont couvertes.
A8: 3 | B8: Opérationnelles | C8: L'entreprise dispose des principales compétences nécessaires pour développer et mettre en œuvre des projets IA. | D8: L'entreprise dispose des principales compétences opérationnelles nécessaires pour développer et mettre en œuvre des projets IA. | E8: Certaines compétences IA pour gagner en profondeur manquent à l'entreprise pour renforcer des dimensions de développement IA/data, ML. | F8: Acquérir une capacité interne couvrant l’ensemble des compétences nécessaires à la mise en œuvre de projets complets IA. | G8: Structurer une capacité opérationnelle couvrant les étapes des projets ; clarifier rôles et collaborations. | H8: L’entreprise peut développer et mettre en œuvre des projets IA avec une capacité interne opérationnelle.
A9: 4 | B9: Complètes | C9: Les compétences couvrent les différentes dimensions nécessaires : data, IA/ML, ingénierie, intégration, déploiement et usages métiers. | D9: L'entreprise possède les ressources avec les compétences complètes qui couvrent les différentes dimensions nécessaires au développement de l'IA : data, IA/ML, ingénierie, intégration, déploiement et usages métiers. | E9: Des compétences IA pour gagner en polyvalence manquent à l'entreprise pour renforcer son autonomie et son innovation multidisciplinaire. | F9: Acquérir une capacité interne multidisciplinaire permettant de concevoir, industrialiser et faire évoluer les solutions IA de manière autonome. | G9: Définir l'ensembel des compétences nécessaires aux usages de l'IA ; constituer des équipes multidisciplinaires ; renforcer interfaces data, IA, ingénierie, intégration, déploiement et métiers. | H9: Les compétences couvrent la chaîne nécessaire pour concevoir, industrialiser et déployer les solutions IA.
A10: 5 | B10: Multidisciplinaires | C10: L'entreprise dispose d'une capacité interne multidisciplinaire permettant de concevoir, industrialiser et faire évoluer des solutions IA de manière autonome. | D10: L'entreprise dispose d'une capacité interne multidisciplinaire permettant de concevoir, industrialiser et faire évoluer des solutions IA de manière autonome. | E10: Bien que les capacités de développement de projets l'IA sont présentes dans l'entreprise une anticipation des besoins de compétences adaptées aux technologies de l'IA en évolution permanente est nécessaire. | F10: Acquérir une capacité interne d'anticipation des besoins en compétences sur les métiers IA en constante évolution. | G10: Mettre en place une veille sur les complétences pro-active ; développer l’autonomie ; organiser capitalisation et partage d’expertise ; anticiper les nouvelles compétences nécessaires. | H10: L’entreprise dispose d’une capacité multidisciplinaire autonome capable de faire évoluer ses solutions IA.

Sheet Q11
A1: {=INDIRECT("IndexQuestions!A" & (A2+3)) & " - " & INDIRECT("IndexQuestions!B" & (A2+3)) & " - " & INDIRECT("IndexQuestions!C" & (A2+3)) & " - " & INDIRECT("IndexQuestions!D" & (A2+3))} -> Q11 - COMPÉTENCES - Structuration - Développement des compétences
A2: {=RIGHT(CELL("nomfichier",A3),2)} -> 11 | B2: {=INDIRECT("IndexQuestions!E" & (A2+3))} -> Dans quelle mesure l’entreprise développe-t-elle les compétences IA de ses collaborateurs ?
A3: Logique | B3: ='Q01'!B3 -> À chaque score : acquis → blocage vers le niveau suivant → capacité à acquérir → actions prioritaires → résultat attendu.
A4: Score | B4: Thème | C4: Réponse | D4: Ce qui est déjà acquis | E4: Ce qui bloque l’étape suivante | F4: Capacités à acquérir | G4: Actions prioritaires | H4: Résultats attendus
A5: 0 | B5: Aucun développement | C5: Aucun dispositif de développement des compétences IA. | D5: Aucun dispositif de développement des compétences IA. | E5: L'entreprise n'a aucun dispositif permettant d'envisager une progression des compétences en IA. | F5: Acquérir la capacité à mettre en place un premier dispositif de développement des compétences IA des collaborateurs. | G5: Identifier populations et compétences prioritaires ; définir un premier dispositif de sensibilisation et de développement. | H5: Un dispositif initial de développement des compétences IA est défini.
A6: 1 | B6: Sensibilisation | C6: Des actions ponctuelles de sensibilisation ou d'initiation sont proposées. | D6: L'entreprise propose des actions ponctuelles de sensibilisation ou d'initiation autour de l'IA. | E6: L'entreprise a peu de dispositif permettant des actions de progression des compétences en IA. | F6: Acquérir la capacité à proposer des actions ciblées de développement des compétences adaptées aux besoins IA identifiés. | G6: Identifier populations et compétences prioritaires ; recueillir les besoins ; Organiser els premières formations. | H6: Les collaborateurs prioritaires disposent d’une première formation aux compétences IA.
A7: 2 | B7: Formation ciblée | C7: Des formations sont proposées à certaines populations ou pour certains besoins. | D7: L'entreprise propose des formations IA à certaines populations ou pour certains besoins. | E7: L'entreprise manque de dispositif structuré et évaluable des parcours de progression des compétences en IA. | F7: Acquérir la capacité à structurer des formations IA adaptées aux différentes populations et aux besoins de l’entreprise. | G7: Définir des parcours de formations adaptées ; structurer contenus ; suivre participation et acquis. | H7: Des parcours de formations ciblées développent les compétences IA sur les besoins identifiés.
A8: 3 | B8: Parcours structurés | C8: Des parcours de développement des compétences sont définis pour différentes catégories de collaborateurs. | D8: L'entreprise développe des parcours structurés de développement des compétences précis pour différentes catégories de collaborateurs. | E8: L'entreprise manque de pilotage des parcours de formation en IA à travers l'identification des besoins de l'entreprise et leur dispense et suivi. | F8: Acquérir la capacité à définir des parcours de développement des compétences IA pour les différentes catégories de collaborateurs. | G8: Construire une GPEC (La Gestion prévisionnelle des emplois et des compétences) au sein de l'entreprise ; construire des parcours par catégories ; définir niveaux, objectifs et modalités ; suivre la progression. | H8: Une GPEC IA. Des parcours structurés développent les compétences IA selon les rôles.
A9: 4 | B9: Gestion des compétences | C9: Les compétences IA sont identifiées, évaluées et développées en fonction des rôles et des besoins de l'entreprise. | D9: L'entreprise possède une gestion de compétences de ses collaborateurs où les savoir faire en IA sont identifiées, évaluées et développées en fonction des rôles et des besoins de l'entreprise. | E9: L'entreprise manque d'une gouvernance complète des compétences en IA afin d'anticiper et actualiser les ressources des projets IA. | F9: Acquérir la capacité à d'entretenir les complétences IA - évaluer les acquis et adapter régulièrement les parcours de développement - en fonction des besoins de l'entreprise. | G9: Cartographier compétences à maintenir par rôle au sein de la GPEC ; évaluer niveaux ; relier écarts aux plans de développement. | H9: La GPEC IA est à jour. Les compétences IA sont identifiées, évaluées et développées selon les besoins.
A10: 5 | B10: Développement continu | C10: L'entreprise dispose d'un dispositif continu permettant d'anticiper les évolutions des compétences IA, d'évaluer les acquis et d'adapter régulièrement les parcours. | D10: L'entreprise dispose d'une gestion des compétences complètes avec un dispositif continu permettant d'anticiper les évolutions des compétences IA, d'évaluer les acquis et d'adapter régulièrement les parcours. | E10: Bien que le développement des compétences IA est présente dans l'entreprise, une anticipation des besoins du marché adaptés aux technologies de l'IA en évolution permanente est nécessaire. | F10: Acquérir la capacité à identifier, évaluer et développer les compétences IA en fonction de l'évolution constante des technologies IA | G10: Mettre en place une veille sur métiers et compétences ; réviser référentiels et parcours ; mesurer les acquis dans la durée. | H10: Le dispositif anticipe les évolutions et adapte continuellement les parcours.

Sheet Q12
A1: {=INDIRECT("IndexQuestions!A" & (A2+3)) & " - " & INDIRECT("IndexQuestions!B" & (A2+3)) & " - " & INDIRECT("IndexQuestions!C" & (A2+3)) & " - " & INDIRECT("IndexQuestions!D" & (A2+3))} -> Q12 - COMPÉTENCES - Industrialisation - Adaptabilité / capacité à combler les lacunes
A2: {=RIGHT(CELL("nomfichier",A3),2)} -> 12 | B2: {=INDIRECT("IndexQuestions!E" & (A2+3))} -> Dans quelle mesure l’entreprise sait-elle identifier et combler ses lacunes en compétences IA ?
A3: Logique | B3: ='Q01'!B3 -> À chaque score : acquis → blocage vers le niveau suivant → capacité à acquérir → actions prioritaires → résultat attendu.
A4: Score | B4: Thème | C4: Réponse | D4: Ce qui est déjà acquis | E4: Ce qui bloque l’étape suivante | F4: Capacités à acquérir | G4: Actions prioritaires | H4: Résultats attendus
A5: 0 | B5: Aucune capacité | C5: Les besoins et lacunes en compétences IA ne sont pas identifiés et aucun recours externe n'est organisé. | D5: L'entreprise n'a pas les capacité d'identifier les besoins et lacunes en compétences IA et aucun recours externe n'est organisé. | E5: L'entreprise n'a pas de mécanisme d'identification au cas par cas des lacunes dans les compétences IA de ses équipes. | F5: Acquérir la capacité à identifier les besoins et lacunes en compétences et à les faire porter en externe. | G5: Identifier besoins critiques ; cartographier lacunes ; définir les premiers moyens internes ou externes pour les combler. | H5: Les principales lacunes sont identifiées et font l’objet d’un premier plan de traitement.
A6: 1 | B6: Réponse ponctuelle | C6: Les compétences manquantes sont traitées au cas par cas, principalement par recours à des prestataires ou experts externes. | D6: L'entreprise traite les compétences manquantes au cas par cas principalement par recours à des prestataires ou experts externes. | E6: L'entreprise a du mal à faire appel régulièrement à des sociétés externes pour compléter ses développements de projets IA répondant aux besoins de l'entreprise. | F6: Acquérir la capacité à traiter de manière structurée les compétences manquantes au-delà des recours ponctuels à des experts externes. | G6: Formaliser le recours aux experts et prestataires ; capitaliser les compétences apportées ; identifier les besoins récurrents. | H6: Les compétences manquantes sont traitées de façon moins ponctuelle et les besoins récurrents sont visibles.
A7: 2 | B7: Recours régulier | C7: L'entreprise fait régulièrement appel à des compétences externes pour compléter ses capacités internes. | D7: L'entreprise fait régulièrement appel à des compétences externes pour compléter ses capacités internes. | E7: L'entreprise n'a pas de stratégie make/buy/partner pour développer ses projets IA répondant aux besoins de l'entreprise. | F7: Acquérir la capacité à prendre des décisions make/buy/partner pour combiner les compétences internes et externes pour répondre aux besoins de l'entreprise. | G7: Analyser régulièrement les besoins ; définir un mix interne/externe ; sélectionner les partenaires nécessaires. | H7: L’entreprise dispose d’un recours externe organisé et complémentaire aux compétences internes.
A8: 3 | B8: Approche structurée | C8: Les lacunes sont identifiées et font l'objet d'une stratégie combinant recrutement, formation et recours à des partenaires externes. | D8: L'entreprise identifie les lacunes de manière structurée en mettant en place une stratégie combinant recrutement, formation et recours à des partenaires externes. | E8: L'entreprise n'a pas de réseau de partenaires pour combler son déficit de compétences internes pour développer ses projets IA, répondant aux besoins de l'entreprise. | F8: Acquérir la capacité à définir une stratégie de partenariat pour le recours de services externes pour combler les lacunes internes. | G8: Cartographier les partenariats possible suivant le domaine d'expertise de l'entreprise et/ou sa stratégie de sous-traitance ; établir une stratégie combinant recrutement, formation, mobilité et partenaires ; suivre écarts et plans de comblement. | H8: Cartographie des partenariats potentiels. Les lacunes sont gérées au moyen d’une stratégie structurée combinant plusieurs leviers.
A9: 4 | B9: Écosystème de compétences | C9: L'entreprise dispose d'un réseau structuré de partenaires, experts, fournisseurs ou institutions permettant de compléter rapidement ses compétences internes. | D9: L'entreprise dispose d'un écosystème structuré de partenaires, experts, fournisseurs ou institutions permettant de compléter rapidement ses compétences internes. | E9: L'entreprise manque d'anticipation de ses besoins en compétences permettant une allocation dynamique de sa stratégie make/buy/partner pour répondre aux besoins de l'entreprise en développement IA. | F9: Acquérir la capacité à anticiper les besoins en compétences et à ajuster continuellement la complémentarité entre développement interne, recrutement, mobilité et écosystème externe. | G9: Structurer un écosystème de partenaires, experts et fournisseurs ; définir les modalités de mobilisation et de transfert. | H9: L’entreprise peut compléter rapidement ses compétences grâce à un écosystème mobilisable.
A10: 5 | B10: Gestion dynamique des capacités | C10: L'entreprise anticipe ses besoins en compétences et ajuste continuellement le mix entre développement interne, recrutement, mobilité et recours à l'écosystème externe. | D10: L'entreprise a une gestion dynamique de ses ressources, en anticipant ses besoins en compétences et en ajustant continuellement le mix entre développement interne, recrutement, mobilité et recours à l'écosystème externe. | E10: Bien que l'industrialisation des compétences IA est présente dans l'entreprise avec une stratégie make/nuy/partners établie, une optimisation de sa dynamique de ces dernières doit être adapté aux technologies de l'IA en évolution permanente pour répondre aux besoins de l'entreprise. | F10: Acquérir la capacité à mobiliser rapidement un réseau structuré pour faire face aux évolutions technologiques et de contexte économique de l'entreprise. | G10: Mettre en place une veille des partenariats pro-active ; mettre en place une gouvernance dynamique à l'écoute de l'ecosystème économique de l'entreprise ; ajuster continuellement recrutement, développement, mobilité et externe. | H10: L’entreprise anticipe ses besoins et ajuste continuellement son mix de compétences.

Sheet Q13
A1: {=INDIRECT("IndexQuestions!A" & (A2+3)) & " - " & INDIRECT("IndexQuestions!B" & (A2+3)) & " - " & INDIRECT("IndexQuestions!C" & (A2+3)) & " - " & INDIRECT("IndexQuestions!D" & (A2+3))} -> Q13 - GOUVERNANCE - Emergence - Cadre et responsabilités
A2: {=RIGHT(CELL("nomfichier",A3),2)} -> 13 | B2: {=INDIRECT("IndexQuestions!E" & (A2+3))} -> Dans quelle mesure l’entreprise dispose-t-elle d’un cadre de gouvernance pour encadrer l’utilisation de l’IA ?
A3: Logique | B3: ='Q01'!B3 -> À chaque score : acquis → blocage vers le niveau suivant → capacité à acquérir → actions prioritaires → résultat attendu.
A4: Score | B4: Thème | C4: Réponse | D4: Ce qui est déjà acquis | E4: Ce qui bloque l’étape suivante | F4: Capacités à acquérir | G4: Actions prioritaires | H4: Résultats attendus
A5: 0 | B5: Aucun cadre | C5: Aucun principe, règle ou responsabilité n'est défini pour l'utilisation de l'IA. | D5: L'entreprise n'a aucun principe, règle ou responsabilité n'est défini pour l'utilisation de l'IA. | E5: L'entreprise manque de cadrage informel pour commencer à définir certaines taches et responsabilités pour l'utilisation de l'IA. | F5: Acquérir la capacité à définir les premiers principes de la gouvernance IA avec des règles et responsabilités encadrant l’utilisation de l’IA. | G5: Identifier les principaux risques et besoins de contrôle liés aux usages de l'IA ; définir premières règles et responsabilités ; sensibiliser les équipes. | H5: Un premier cadre de principes, règles et responsabilités encadre les usages IA prioritaires.
A6: 1 | B6: Principes informels | C6: Des principes ou consignes existent, mais ils restent informels et peu diffusés. | D6: L'entreprise donne des principes ou consignes qui restent informels et peu diffusés. | E6: L'entreprise manque de définition de règles non formalisées néanmoins diffusées pour certains usages. | F6: Acquérir la capacité à formaliser et diffuser les principes et consignes applicables à l’utilisation de l’IA. | G6: Formaliser les principes ; les diffuser ; définir responsabilités et règles applicables aux premiers usages. | H6: Les principes et consignes IA sont formalisés et connus des populations concernées.
A7: 2 | B7: Règles partielles | C7: Des règles existent pour certains usages ou risques, mais leur couverture reste limitée. | D7: L'entreprise définit des règles pour certains usages ou risques, mais leur couverture reste partielle et limitée. | E7: L'entreprise manque d'un cadre formalisé définissant a minima les principales règles d'utilisation de l'IA et des responsabilités associées et un début de couverture des risques. | F7: Acquérir la capacité à étendre les règles d’utilisation de l’IA aux principaux usages et risques concernés. | G7: Standardiser les règles aux principaux usages et risques ; documenter responsabilités ; identifier contrôles complémentaires. | H7: Les principaux usages et risques sont standardiser au sein de l'entreprise qui dispose de règles et responsabilités identifiées.
A8: 3 | B8: Cadre formalisé | C8: Un cadre formalisé définit les principales règles, responsabilités et conditions d'utilisation de l'IA. | D8: L'entreprise définit un cadre formalisé avec les principales règles, responsabilités et conditions d'utilisation de l'IA. | E8: L'entreprise manque d'une gouvernance structurée définissant les risques, la sécurité, les données, la conformité, l'éthique et les responsabilités, avec des rôles clairement définis. | F8: Acquérir la capacité à disposer d’une gouvernance structurée de l'IA définissant les risques, la sécurité, les données, la conformité, l'éthique et les responsabilités, avec des rôles clairement définis. | G8: Formaliser le gouvernance ; définir rôles, responsabilités, processus et conditions d’utilisation ; organiser son application. | H8: Un gouvernance IA formalisée encadre les principaux projets et usages IA.
A9: 4 | B9: Gouvernance structurée | C9: Le cadre couvre notamment les risques, la sécurité, les données, la conformité, l'éthique et les responsabilités, avec des rôles clairement définis. | D9: Le gouvernance structuré d'usage de l'IA en entreprise couvre notamment les risques, la sécurité, les données, la conformité, l'éthique et les responsabilités, avec des rôles clairement définis. | E9: L'entreprise n'a pas une gouvernance suffisante de l'utilisation de l'IA intégrée à ses processus permettant une évolution continue en fonction des évolutions de l'écosystème d'entreprise. | F9: Acquérir la capacité à intégrer la gouvernance IA dans les processus de l’entreprise et à la faire évoluer en fonction des risques, usages, réglementations et pratiques de référence. | G9: Intégrer la gouvernacne IA dans les procesus d'entreprise : couvrir risques, sécurité, données, conformité, éthique et responsabilités ; mettre en place instances et contrôles. | H9: Une gouvernance IA intégrée aux processus d'entreprise couvre les principales dimensions de risque avec des responsabilités claires.
A10: 5 | B10: Gouvernance intégrée | C10: La gouvernance IA est intégrée aux processus de l'entreprise et évolue régulièrement en fonction des risques, des usages, des réglementations et des pratiques de référence. | D10: La gouvernance IA est intégrée aux processus de l'entreprise et évolue régulièrement en fonction des risques, des usages, des réglementations et des pratiques de référence. | E10: Bien que l'émergence d'une gouvernance de l'utilisation de l'IA existe dans l'entreprise, une anticipation d'une gouvernance IA adaptés aux évolutions permanentes technologiques et règlementaires de l'IA est nécessaire. | F10: Acquérir la capacité à couvrir de manière structurée l'ensemble des évolutions technologiques et réglementaires de l'IA. | G10: Assurer une veille réglementaire, méthodologique et technologique; réviser règles et contrôles. | H10: La gouvernance IA est intégrée au fonctionnement de l'entreprise et bénéficie des veilles réglementaire, méthodologique et technologique.

Sheet Q14
A1: {=INDIRECT("IndexQuestions!A" & (A2+3)) & " - " & INDIRECT("IndexQuestions!B" & (A2+3)) & " - " & INDIRECT("IndexQuestions!C" & (A2+3)) & " - " & INDIRECT("IndexQuestions!D" & (A2+3))} -> Q14 - GOUVERNANCE - Structuration - Évaluation & validation
A2: {=RIGHT(CELL("nomfichier",A3),2)} -> 14 | B2: {=INDIRECT("IndexQuestions!E" & (A2+3))} -> Dans quelle mesure les projets et usages d’IA font-ils l’objet d’une évaluation et d’une validation avant leur mise en production ?
A3: Logique | B3: ='Q01'!B3 -> À chaque score : acquis → blocage vers le niveau suivant → capacité à acquérir → actions prioritaires → résultat attendu.
A4: Score | B4: Thème | C4: Réponse | D4: Ce qui est déjà acquis | E4: Ce qui bloque l’étape suivante | F4: Capacités à acquérir | G4: Actions prioritaires | H4: Résultats attendus
A5: 0 | B5: Aucune évaluation | C5: Les solutions IA peuvent être déployées sans processus d'évaluation ou de validation. | D5: Au sein de l'entreprise, les solutions IA peuvent être déployées sans processus d'évaluation ou de validation. | E5: L'entreprise ne controle pas les déploiements des projets et usages IA. | F5: Acquérir la capacité à évaluer et valider certaines solutions IA avant leur mise en production. | G5: Définir des critères minimaux ; identifier les projets soumis à validation ; formaliser une première revue avant mise en production. | H5: Les projets IA font l’objet d’une première évaluation avant déploiement.
A6: 1 | B6: Évaluation ponctuelle | C6: Certains projets font l'objet d'une évaluation informelle avant leur déploiement. | D6: L'entreprise met en place ponctuellement une évaluation informelle avant leur déploiement de certains projets font l'objet | E6: L'entreprise manque d'approche systématique dans l'évaluation de certains projets et d'usages IA. | F6: Acquérir la capacité à appliquer de manière systématique certain critères d'évaluation avant le déploiement des projets IA. | G6: Formaliser les évaluations ; définir responsabilités de validation ; conserver décisions et éléments d’analyse. | H6: Les projets concernés sont évalués selon un processus identifiable avant production.
A7: 2 | B7: Évaluation partielle | C7: Des critères d'évaluation existent pour certains projets ou certains types de risques. | D7: L'entreprise demande la mise en place de critères d'évaluation partielle pour certains projets ou certains types de risques. | E7: L'entreprise manque de critères formalisés lors de la mise en production de projets et d'usages IA pour limiter les risques. | F7: Acquérir la capacité à étendre un processus formalisé d’évaluation aux différents projets et types de risques concernés. | G7: Standardiser les critères d'évaluation et validation des projets et des risques ; définir seuils ou conditions de validation adaptés. | H7: Les principaux projets et types de risques disposent de critères d’évaluation identifiés avec des standards d'entreprise.
A8: 3 | B8: Processus structuré | C8: Un processus formalisé évalue les projets selon des critères définis avant leur mise en production. | D8: L'entreprise a mis en place un processus formalisé d'évaluation structurée des projets IA selon des critères définis avant leur mise en production. | E8: Des critères multidimensionnels tel que performance, sécurité, données, risques, conformité, impacts et responsabilités, manquent lors de l'évaluation des projets et d'usages d'IA | F8: Acquérir la capacité à appliquer un processus formalisé évaluant les projets IA selon des critères de performance, de sécurité, des données, des risques, de conformité, des impacts et des responsabilités avant leur mise en production. | G8: Mettre en œuvre des capacité d'audits de la mise en production des porjets IA ; standardiser les dossiers ; assurer la traçabilité des décisions. | H8: Chaque projet concerné est audité selon un processus qualité avant production.
A9: 4 | B9: Évaluation multidimensionnelle | C9: L'évaluation couvre systématiquement les dimensions pertinentes : performance, sécurité, données, risques, conformité, impacts et responsabilités. | D9: L'entreprise a définit une évaluation systématique des dimensions pertinentes des projets IA: performance, sécurité, données, risques, conformité, impacts et responsabilités. | E9: Il y a un manque de traçabilité et d'adapation au contexte d'utilisation pour générer les niveaux d'évaluation des projets et d'usages d'IA. | F9: Acquérir la capacité à décider systématiquement les solutions IA selon les dimensions de performance, sécurité, données, risques, conformité, impacts et responsabilités. | G9: Intégrer performance, sécurité, données, risques, conformité, impacts et responsabilités selon les cas au sein des standard d'audit des protejs IA. | H9: Les décisions de mise en production reposent sur une évaluation multidimensionnelle standardisée.
A10: 5 | B10: Décision fondée sur les risques | C10: Le niveau d'évaluation et de validation est adapté au niveau de risque et au contexte de chaque usage IA, avec traçabilité des décisions et réévaluation lorsque nécessaire. | D10: La gouvernance de projets IA est fondée sur la gestion des risques et le niveau d'évaluation et de validation est adapté au niveau de risque et au contexte de chaque usage IA, avec traçabilité des décisions et réévaluation lorsque nécessaire. | E10: Bien que l'évaluation et la validation des projets et usages IA sont standardisés, une anticipation des risques et usages émergents doit être amenée, et industrialisée de manière à controler l'ensemble du cycle de vie des usages de l'IA. | F10: Acquérir la capacité à adapter le niveau d’évaluation et de validation au risque et au contexte de chaque usage IA avec traçabilité et réévaluation lorsque nécessaire. | G10: Adapter le niveau d’évaluation au risque et au contexte ; tracer les décisions ; déclencher les réévaluations nécessaires. | H10: Les audits qualités des projets IA sont proportionnées aux risques et restent traçables lorsque les conditions évoluent.

Sheet Q15
A1: {=INDIRECT("IndexQuestions!A" & (A2+3)) & " - " & INDIRECT("IndexQuestions!B" & (A2+3)) & " - " & INDIRECT("IndexQuestions!C" & (A2+3)) & " - " & INDIRECT("IndexQuestions!D" & (A2+3))} -> Q15 - GOUVERNANCE - Industrialisation - Surveillance & cycle de vie
A2: {=RIGHT(CELL("nomfichier",A3),2)} -> 15 | B2: {=INDIRECT("IndexQuestions!E" & (A2+3))} -> Dans quelle mesure les solutions IA déployées sont-elles surveillées et réévaluées pendant leur cycle de vie ?
A3: Logique | B3: ='Q01'!B3 -> À chaque score : acquis → blocage vers le niveau suivant → capacité à acquérir → actions prioritaires → résultat attendu.
A4: Score | B4: Thème | C4: Réponse | D4: Ce qui est déjà acquis | E4: Ce qui bloque l’étape suivante | F4: Capacités à acquérir | G4: Actions prioritaires | H4: Résultats attendus
A5: 0 | B5: Aucun suivi | C5: Les solutions IA ne font pas l'objet d'un suivi après leur déploiement. | D5: L'entreprise n'a pas mis en place de suivit des solutions IA après leur déploiement. | E5: Le fonctionnement des solutions IA n'est pas vérifié ponctuellement, généralement en cas de problème et des dérive non détectées sont possibles. | F5: Acquérir la capacité à suivre les solutions IA ponctuellement après leur déploiement. | G5: Identifier les solutions IA en exploitation ; définir indicateurs et responsabilités ; mettre en place un premier contrôle post-déploiement. | H5: Les solutions IA déployées sont identifiées et font l’objet d’un premier suivi.
A6: 1 | B6: Suivi ponctuel | C6: Le fonctionnement des solutions est vérifié ponctuellement, généralement en cas de problème. | D6: Le fonctionnement des solutions est vérifié ponctuellement, généralement en cas de problème par l'entreprise. | E6: Le fonctionnement des solutions est vérifié insuffisamment, sans metrique et inégalement, et les problèmes sont détectés tardivement. | F6: Acquérir la capacité à vérifier régulièrement des solutions IA avec certaines metriques et à déclenchées des interventrion lors de problèmes. | G6: Planifier des vérifications régulières ; définir seuils d’alerte ; documenter incidents et actions correctives (ouvir un portail de ticketing). | H6: Le fonctionnement des solutions IA est vérifié régulièrement et les problèmes sont tracés. Les premires tickets sont traités.
A7: 2 | B7: Suivi partiel | C7: Certaines métriques ou retours utilisateurs sont suivis, mais de manière inégale. | D7: L'entreprise a mis en place certaines métriques ou le suivi des retours utilisateurs, mais de manière inégale. | E7: Le fonctionnement des solutions n'est pas suivi avec des indicateurs réguliers entrainant une couverture et une automatisation inégales. | F7: Acquérir la capacité à généraliser le suivi des métriques et des retours utilisateurs aux différentes solutions IA. | G7: Standardiser le suivi des métriques et retours utilisateurs ; harmoniser indicateurs et responsabilités. | H7: Les principales solutions disposent d’un suivi homogène des indicateurs et retours au sein de portail de suivi.
A8: 3 | B8: Suivi structuré | C8: Des indicateurs sont définis et suivis régulièrement pour les solutions IA en production. | D8: L'entreprise a défini des indicateurs de suivi structuré régulièrement pour les solutions IA en production. | E8: Un monitoring multidimensionnel est manquant pour suivre performance, qualité, sécurité, coûts, dérive des modèles et retours utilisateurs, avec des mécanismes d'alerte et d'action. | F8: Acquérir la capacité à définir et suivre régulièrement des indicateurs multidimensionels permettant de surveiller les solutions IA en exploitation, notamment sur la performance, la qualité, la sécurité, les coûts, la dérive des modèles et les retours utilisateurs, avec des mécanismes d'alerte et d'action.. | G8: Définir des indicateurs structurés ; automatiser leur collecte lorsque possible ; organiser revues et traitement des écarts. | H8: Les solutions en production font l’objet d’un suivi régulier et structuré avec actions correctives.
A9: 4 | B9: Suivi continu | C9: Le suivi couvre notamment performance, qualité, sécurité, coûts, dérive des modèles et retours utilisateurs, avec des mécanismes d'alerte et d'action. | D9: Le suivi continu de l'entreprise couvre notamment performance, qualité, sécurité, coûts, dérive des modèles et retours utilisateurs, avec des mécanismes d'alerte et d'action. | E9: L'entreprise ne réévalue pas les solutions IA déployées permettant de les adapter au contexte de l'entreprise et/ou de les retirer lors d'une élévation des risques de leurs usages | F9: Acquérir la capacité à surveiller et réévaluer les solutions IA sur l’ensemble de leur cycle de vie et à les adapter, suspendre ou retirer lorsque les conditions ou les risques évoluent. | G9: Étendre le suivi à performance, qualité, sécurité, coûts, dérive et retours utilisateurs ; mettre en place alertes. | H9: L’entreprise dispose d’un suivi continu permettant de détecter les dérives et d’agir rapidement.
A10: 5 | B10: Gouvernance du cycle de vie | C10: Les solutions IA sont surveillées et réévaluées sur l'ensemble de leur cycle de vie, avec des mécanismes permettant d'adapter, suspendre ou retirer une solution lorsque les conditions ou les risques évoluent. | D10: Une gouvernance complète est mis en place en surveillant et réévaluant sur l'ensemble de leur cycle de vie les solutions IA, avec des mécanismes permettant d'adapter, suspendre ou retirer une solution lorsque les conditions ou les risques évoluent. | E10: Bien que la surveillace du cycle de vie des projets et usages IA existe dans l'entreprise, une anticipation des risques et usages émergents doit être structurée, pour répondre aux évolutions technologiques rapides du marché de l'IA. | F10: Acquérir la capacité à adapter la gouvernance du cycle de vie de chaque usage IA avec traçabilité et réévaluation lorsque nécessaire, notamment suite à un changement réglementaire. | G10: Assurer une veille réglementaire, méthodologique et technologique; intégrer le monitoring au cycle de vie ; organiser réévaluations ; définir mécanismes d’adaptation, suspension ou retrait. | H10: Les solutions IA sont gouvernées sur tout leur cycle de vie et peuvent être adaptées, suspendues ou retirées en fonction du contexte économique, technologique ou réglementaire.
